{
  "row": {
    "variant": "conditional_current_matching",
    "seed": 2,
    "checkpoint": 4000,
    "score_main": 0.3640305538598092,
    "tstr_macro_f1": 0.2514877710389371,
    "disc_auc_gap": 0.13828428610533539,
    "unconditional_w1": 0.18754139314182475,
    "conditional_w1": 0.4897997422624652,
    "train_seconds": 592.497686624527,
    "eval_seconds": 55.294599771499634
  },
  "result": {
    "10": {
      "gen": {
        "depth_mean": {
          "mean": 513.4211107889811,
          "std": 145.39583572082728
        },
        "imb_mean": {
          "mean": -0.009085406394054493,
          "std": 0.1904982314558046
        },
        "imb_std": {
          "mean": 0.4338135501990716,
          "std": 0.1078692038723824
        },
        "spread_mean": {
          "mean": 0.000685818250834321,
          "std": 0.00018611220296058483
        },
        "spread_std": {
          "mean": 0.00025499280673102476,
          "std": 7.807827872687897e-05
        }
      },
      "true": {
        "depth_mean": {
          "mean": 589.2374992370605,
          "std": 278.6610566444663
        },
        "imb_mean": {
          "mean": 0.01892832911107689,
          "std": 0.35098768271821307
        },
        "imb_std": {
          "mean": 0.28401869411269826,
          "std": 0.12280290546066167
        },
        "spread_mean": {
          "mean": 0.0009113465706226028,
          "std": 0.000534738865534999
        },
        "spread_std": {
          "mean": 0.00023493807141979536,
          "std": 0.00020877709384882335
        }
      },
      "cmp": {
        "basic_gen": {
          "depth_mean": {
            "mean": 513.4211107889811,
            "std": 145.39583572082728
          },
          "imb_mean": {
            "mean": -0.009085406394054493,
            "std": 0.1904982314558046
          },
          "imb_std": {
            "mean": 0.4338135501990716,
            "std": 0.1078692038723824
          },
          "spread_mean": {
            "mean": 0.000685818250834321,
            "std": 0.00018611220296058483
          },
          "spread_std": {
            "mean": 0.00025499280673102476,
            "std": 7.807827872687897e-05
          }
        },
        "basic_true": {
          "depth_mean": {
            "mean": 589.2374992370605,
            "std": 278.6610566444663
          },
          "imb_mean": {
            "mean": 0.01892832911107689,
            "std": 0.35098768271821307
          },
          "imb_std": {
            "mean": 0.28401869411269826,
            "std": 0.12280290546066167
          },
          "spread_mean": {
            "mean": 0.0009113465706226028,
            "std": 0.000534738865534999
          },
          "spread_std": {
            "mean": 0.00023493807141979536,
            "std": 0.00020877709384882335
          }
        },
        "dist": {
          "depth": {
            "ks": {
              "mean": 0.4375,
              "std": 0.20577597041442908
            },
            "w1": {
              "mean": 199.01409861326215,
              "std": 188.46749065130967
            }
          },
          "imb": {
            "ks": {
              "mean": 0.4916666666666667,
              "std": 0.19982631347136331
            },
            "w1": {
              "mean": 0.3823117581578192,
              "std": 0.2725380362867568
            }
          },
          "ret": {
            "ks": {
              "mean": 0.3791666666666667,
              "std": 0.1224035901797365
            },
            "w1": {
              "mean": 9.277662883202234e-05,
              "std": 5.572744748429539e-05
            }
          },
          "spread": {
            "ks": {
              "mean": 0.6291666666666668,
              "std": 0.21110654234822337
            },
            "w1": {
              "mean": 0.00035324158767859135,
              "std": 0.0003661240606962029
            }
          }
        },
        "error": {
          "imbalance_mae": {
            "mean": 4.958313416220418,
            "std": 14.088658047604252
          },
          "spread_mae": {
            "mean": 2.984733879675073,
            "std": 3.1627585795541195
          }
        },
        "microstructure": {
          "impact_response_curve_gen": {
            "1": {
              "mean": -2.530984430007909e-06,
              "std": 2.8303194548482596e-05
            },
            "5": {
              "mean": 1.7518864283261323e-05,
              "std": 0.00011076020233597326
            }
          },
          "impact_response_curve_true": {
            "1": {
              "mean": -1.3499200407184216e-06,
              "std": 3.0515356132687764e-05
            },
            "5": {
              "mean": 1.6469285592126246e-05,
              "std": 0.00019346063092708405
            }
          },
          "impact_response_l1": {
            "mean": 3.934915761079401,
            "std": 5.506918311066843
          }
        },
        "params_fit": {
          "delta_mid_rmse": {
            "mean": 0.0002707024435342949,
            "std": 0.00011889680725351658
          },
          "log_spread_rmse": {
            "mean": 0.7004368243118128,
            "std": 0.2372973593065715
          },
          "params_mae": {
            "mean": 1.1746895934144657,
            "std": 0.22205865352541362
          },
          "params_rmse": {
            "mean": 1.7301505953073502,
            "std": 0.3141090366704962
          }
        },
        "score_main": {
          "mean": 0.4050747699597509,
          "std": 0.0
        },
        "structure": {
          "vol_corr_mae": {
            "mean": 0.3060721152621982,
            "std": 0.09993292651468481
          },
          "vol_corr_rmse": {
            "mean": 0.4267090314326387,
            "std": 0.1309028656721167
          }
        },
        "temporal": {
          "depth": {
            "acf_l1": {
              "mean": 0.24232152382824892,
              "std": 0.05846279908931396
            },
            "acf_l2": {
              "mean": 0.4643730016870354,
              "std": 0.11489697185571361
            }
          },
          "imb": {
            "acf_l1": {
              "mean": 0.2635897141515917,
              "std": 0.06463581650241684
            },
            "acf_l2": {
              "mean": 0.5147765587990878,
              "std": 0.15153703885280795
            }
          },
          "ret": {
            "acf_l1": {
              "mean": 0.1756334722905263,
              "std": 0.054955726174182
            },
            "acf_l2": {
              "mean": 0.33245437485749185,
              "std": 0.10480086860883242
            }
          },
          "spread": {
            "acf_l1": {
              "mean": 0.23687879017364102,
              "std": 0.08981545638245399
            },
            "acf_l2": {
              "mean": 0.45004759798937144,
              "std": 0.15288629933825662
            }
          },
          "volatility": {
            "acf_l1": {
              "mean": 0.19819745677318865,
              "std": 0.10170732188589164
            },
            "acf_l2": {
              "mean": 0.36748560053297213,
              "std": 0.19079070031345882
            }
          }
        },
        "validity": {
          "ask_monotonic_violation_rate": {
            "mean": 0.0,
            "std": 0.0
          },
          "bid_monotonic_violation_rate": {
            "mean": 0.0,
            "std": 0.0
          },
          "crossed_rate": {
            "mean": 0.0,
            "std": 0.0
          },
          "nonpositive_volume_rate": {
            "mean": 0.0,
            "std": 0.0
          },
          "valid_rate": {
            "mean": 1.0,
            "std": 0.0
          }
        },
        "main": {
          "tstr_macro_f1": {
            "mean": 0.16167003367003366,
            "std": 0.0
          },
          "disc_auc": {
            "mean": 0.626508875739645,
            "std": 0.0
          },
          "disc_auc_gap": {
            "mean": 0.12650887573964498,
            "std": 0.0
          },
          "unconditional_w1": {
            "mean": 0.2226104345321174,
            "std": 0.0
          },
          "conditional_w1": {
            "mean": 0.5753413272097362,
            "std": 0.0
          },
          "label_horizon": 1,
          "n_examples_real": 216,
          "n_examples_gen": 216,
          "threshold_abs_move": {
            "mean": 0.0,
            "std": 0.0
          },
          "unconditional_w1_by_stat": {
            "spread": {
              "mean": 0.3710459314888569,
              "std": 0.0
            },
            "depth": {
              "mean": 0.19840496164584231,
              "std": 0.0
            },
            "imb": {
              "mean": 0.14259339454911382,
              "std": 0.0
            },
            "ret": {
              "mean": 0.1783974504446566,
              "std": 0.0
            }
          },
          "conditional_w1_by_stat": {
            "spread": {
              "mean": 0.568583833156245,
              "std": 0.0
            },
            "depth": {
              "mean": 0.5225181867365456,
              "std": 0.0
            },
            "imb": {
              "mean": 0.8170612923316481,
              "std": 0.0
            },
            "ret": {
              "mean": 0.393201996614506,
              "std": 0.0
            }
          },
          "stat_scales": {
            "spread": {
              "mean": 0.0006212656200893452,
              "std": 0.0
            },
            "depth": {
              "mean": 380.8749698383328,
              "std": 0.0
            },
            "imb": {
              "mean": 0.46791074518634457,
              "std": 0.0
            },
            "ret": {
              "mean": 0.00023595157102668593,
              "std": 0.0
            }
          }
        },
        "extra": {
          "u_l1": {
            "mean": 0.6104166666666666,
            "std": 0.0
          },
          "c_l1": {
            "mean": 3.019699764146072,
            "std": 0.0
          },
          "spread_specific_error": {
            "mean": 2.984733879675073,
            "std": 3.1627585795541195
          },
          "imbalance_specific_error": {
            "mean": 4.958313416220418,
            "std": 14.088658047604252
          },
          "ret_vol_acf_error": {
            "mean": 0.18691546453185748,
            "std": 0.0
          },
          "impact_response_error": {
            "mean": 3.934915761079401,
            "std": 5.506918311066843
          },
          "efficiency_ms_per_sample": {
            "mean": 227.83107461873442,
            "std": 0.45070438408899677
          }
        },
        "legacy_score_main": {
          "mean": 2.2885418439722063,
          "std": 0.4972768614084219
        }
      },
      "horizon": {
        "10": {
          "delta_mid_rmse": {
            "mean": 0.0002707024435342949,
            "std": 0.00011889680725351658
          },
          "log_spread_rmse": {
            "mean": 0.7004368243118128,
            "std": 0.2372973593065715
          },
          "params_mae": {
            "mean": 1.1746895934144657,
            "std": 0.22205865352541362
          },
          "params_rmse": {
            "mean": 1.7301505953073502,
            "std": 0.3141090366704962
          }
        }
      },
      "timing": {
        "horizon": {
          "mean": 10.0,
          "std": 0.0
        },
        "latency_ms_per_sample": {
          "mean": 227.83107461873442,
          "std": 0.45070438408899677
        },
        "latency_ms_per_step": {
          "mean": 22.783107461873442,
          "std": 0.04507043840889967
        },
        "latency_s_total": {
          "mean": 0.22783107461873442,
          "std": 0.00045070438408899673
        },
        "nfe": {
          "mean": 4.0,
          "std": 0.0
        },
        "throughput_steps_per_s": {
          "mean": 43.8923399910085,
          "std": 0.08650399489922216
        }
      },
      "meta": {
        "n_windows": 24,
        "nfe": 4,
        "horizon": 10
      }
    },
    "30": {
      "gen": {
        "depth_mean": {
          "mean": 529.9669965108236,
          "std": 62.037163279430295
        },
        "imb_mean": {
          "mean": -0.030270503295469098,
          "std": 0.12735298950909268
        },
        "imb_std": {
          "mean": 0.4445788065592448,
          "std": 0.049305280191357215
        },
        "spread_mean": {
          "mean": 0.0005864722855524936,
          "std": 0.00013372580314370753
        },
        "spread_std": {
          "mean": 0.00026979537930553005,
          "std": 9.042790401606685e-05
        }
      },
      "true": {
        "depth_mean": {
          "mean": 594.2805544535319,
          "std": 248.69065363921928
        },
        "imb_mean": {
          "mean": -0.10426190107439955,
          "std": 0.2775886049396182
        },
        "imb_std": {
          "mean": 0.3740973665068547,
          "std": 0.11663236031412276
        },
        "spread_mean": {
          "mean": 0.0007223693016082203,
          "std": 0.0004899053843570229
        },
        "spread_std": {
          "mean": 0.0002081772436213214,
          "std": 0.00016217169589398037
        }
      },
      "cmp": {
        "basic_gen": {
          "depth_mean": {
            "mean": 529.9669965108236,
            "std": 62.037163279430295
          },
          "imb_mean": {
            "mean": -0.030270503295469098,
            "std": 0.12735298950909268
          },
          "imb_std": {
            "mean": 0.4445788065592448,
            "std": 0.049305280191357215
          },
          "spread_mean": {
            "mean": 0.0005864722855524936,
            "std": 0.00013372580314370753
          },
          "spread_std": {
            "mean": 0.00026979537930553005,
            "std": 9.042790401606685e-05
          }
        },
        "basic_true": {
          "depth_mean": {
            "mean": 594.2805544535319,
            "std": 248.69065363921928
          },
          "imb_mean": {
            "mean": -0.10426190107439955,
            "std": 0.2775886049396182
          },
          "imb_std": {
            "mean": 0.3740973665068547,
            "std": 0.11663236031412276
          },
          "spread_mean": {
            "mean": 0.0007223693016082203,
            "std": 0.0004899053843570229
          },
          "spread_std": {
            "mean": 0.0002081772436213214,
            "std": 0.00016217169589398037
          }
        },
        "dist": {
          "depth": {
            "ks": {
              "mean": 0.38472222222222224,
              "std": 0.1557476492500403
            },
            "w1": {
              "mean": 198.4101199120062,
              "std": 153.6852998637032
            }
          },
          "imb": {
            "ks": {
              "mean": 0.37777777777777777,
              "std": 0.17812466157645998
            },
            "w1": {
              "mean": 0.26233341472065835,
              "std": 0.17495452312067744
            }
          },
          "ret": {
            "ks": {
              "mean": 0.34722222222222215,
              "std": 0.0985621944400565
            },
            "w1": {
              "mean": 5.931929719668846e-05,
              "std": 3.447823473085098e-05
            }
          },
          "spread": {
            "ks": {
              "mean": 0.4750000000000001,
              "std": 0.17539637649874323
            },
            "w1": {
              "mean": 0.00025565731028715774,
              "std": 0.0003255511201152236
            }
          }
        },
        "error": {
          "imbalance_mae": {
            "mean": 1.5477817722852862,
            "std": 0.46526280785909024
          },
          "spread_mae": {
            "mean": 1.8540111534835535,
            "std": 0.7090722735494566
          }
        },
        "microstructure": {
          "impact_response_curve_gen": {
            "1": {
              "mean": 1.2889384309351225e-07,
              "std": 1.4058163576758372e-05
            },
            "10": {
              "mean": -6.900505351842741e-06,
              "std": 5.569008795632816e-05
            },
            "20": {
              "mean": -2.8618905088184077e-05,
              "std": 0.00015639938646506033
            },
            "5": {
              "mean": -5.1109151870560005e-06,
              "std": 3.3901801772154324e-05
            }
          },
          "impact_response_curve_true": {
            "1": {
              "mean": 6.894808477144089e-06,
              "std": 2.1800404903805622e-05
            },
            "10": {
              "mean": 4.427161801331052e-05,
              "std": 0.00019252339253165925
            },
            "20": {
              "mean": 0.00010599963601856091,
              "std": 0.00033670226032406263
            },
            "5": {
              "mean": 3.2459603935918875e-05,
              "std": 8.789137694829075e-05
            }
          },
          "impact_response_l1": {
            "mean": 4.348230140391137,
            "std": 6.589125159315223
          }
        },
        "params_fit": {
          "delta_mid_rmse": {
            "mean": 0.00021942037043724363,
            "std": 9.923426306777983e-05
          },
          "log_spread_rmse": {
            "mean": 0.6632894563178221,
            "std": 0.186166597725504
          },
          "params_mae": {
            "mean": 1.1527160331606865,
            "std": 0.21919578205666773
          },
          "params_rmse": {
            "mean": 1.697539582848549,
            "std": 0.29027879412752117
          }
        },
        "score_main": {
          "mean": 0.36017907166594,
          "std": 0.0
        },
        "structure": {
          "vol_corr_mae": {
            "mean": 0.20403091236238968,
            "std": 0.08329371290449816
          },
          "vol_corr_rmse": {
            "mean": 0.28214400686428026,
            "std": 0.10760401735693897
          }
        },
        "temporal": {
          "depth": {
            "acf_l1": {
              "mean": 0.3336100734107461,
              "std": 0.08681061039985632
            },
            "acf_l2": {
              "mean": 0.40342976449556306,
              "std": 0.09277287271489727
            }
          },
          "imb": {
            "acf_l1": {
              "mean": 0.3239339751320031,
              "std": 0.08238082445741264
            },
            "acf_l2": {
              "mean": 0.392994187975022,
              "std": 0.08707288516257079
            }
          },
          "ret": {
            "acf_l1": {
              "mean": 0.23805189961010886,
              "std": 0.054817813040342875
            },
            "acf_l2": {
              "mean": 0.297446882610885,
              "std": 0.062401889263577884
            }
          },
          "spread": {
            "acf_l1": {
              "mean": 0.2832835430373974,
              "std": 0.08559720954043068
            },
            "acf_l2": {
              "mean": 0.34440751175808487,
              "std": 0.10357399507279619
            }
          },
          "volatility": {
            "acf_l1": {
              "mean": 0.334635345582861,
              "std": 0.15662473292347248
            },
            "acf_l2": {
              "mean": 0.40068087345676906,
              "std": 0.18174651200546904
            }
          }
        },
        "validity": {
          "ask_monotonic_violation_rate": {
            "mean": 0.0,
            "std": 0.0
          },
          "bid_monotonic_violation_rate": {
            "mean": 0.0,
            "std": 0.0
          },
          "crossed_rate": {
            "mean": 0.0,
            "std": 0.0
          },
          "nonpositive_volume_rate": {
            "mean": 0.0,
            "std": 0.0
          },
          "valid_rate": {
            "mean": 1.0,
            "std": 0.0
          }
        },
        "main": {
          "tstr_macro_f1": {
            "mean": 0.28257556693301067,
            "std": 0.0
          },
          "disc_auc": {
            "mean": 0.6647358911680306,
            "std": 0.0
          },
          "disc_auc_gap": {
            "mean": 0.16473589116803056,
            "std": 0.0
          },
          "unconditional_w1": {
            "mean": 0.1869161288958363,
            "std": 0.0
          },
          "conditional_w1": {
            "mean": 0.47284736072193695,
            "std": 0.0
          },
          "label_horizon": 3,
          "n_examples_real": 648,
          "n_examples_gen": 648,
          "threshold_abs_move": {
            "mean": 2.8709571779472753e-05,
            "std": 0.0
          },
          "unconditional_w1_by_stat": {
            "spread": {
              "mean": 0.2417966497461732,
              "std": 0.0
            },
            "depth": {
              "mean": 0.18574643125220222,
              "std": 0.0
            },
            "imb": {
              "mean": 0.1565439258881695,
              "std": 0.0
            },
            "ret": {
              "mean": 0.16357750869680035,
              "std": 0.0
            }
          },
          "conditional_w1_by_stat": {
            "spread": {
              "mean": 0.4586132632997578,
              "std": 0.0
            },
            "depth": {
              "mean": 0.5230631607027565,
              "std": 0.0
            },
            "imb": {
              "mean": 0.5462810086947426,
              "std": 0.0
            },
            "ret": {
              "mean": 0.3634320101904909,
              "std": 0.0
            }
          },
          "stat_scales": {
            "spread": {
              "mean": 0.0005574572973482792,
              "std": 0.0
            },
            "depth": {
              "mean": 379.32344469726024,
              "std": 0.0
            },
            "imb": {
              "mean": 0.4802169772430221,
              "std": 0.0
            },
            "ret": {
              "mean": 0.00016321979224008523,
              "std": 0.0
            }
          }
        },
        "extra": {
          "u_l1": {
            "mean": 0.4354166666666666,
            "std": 0.0
          },
          "c_l1": {
            "mean": 1.536737314480975,
            "std": 0.0
          },
          "spread_specific_error": {
            "mean": 1.8540111534835535,
            "std": 0.7090722735494566
          },
          "imbalance_specific_error": {
            "mean": 1.5477817722852862,
            "std": 0.46526280785909024
          },
          "ret_vol_acf_error": {
            "mean": 0.28634362259648494,
            "std": 0.0
          },
          "impact_response_error": {
            "mean": 4.348230140391137,
            "std": 6.589125159315223
          },
          "efficiency_ms_per_sample": {
            "mean": 683.8586687420806,
            "std": 0.6677174340056111
          }
        },
        "legacy_score_main": {
          "mean": 2.1982398737868,
          "std": 0.3943589913178935
        }
      },
      "horizon": {
        "10": {
          "delta_mid_rmse": {
            "mean": 0.00021272220237733563,
            "std": 0.0001390360066829272
          },
          "log_spread_rmse": {
            "mean": 0.6207924957076708,
            "std": 0.23467957792318653
          },
          "params_mae": {
            "mean": 1.1861530244350433,
            "std": 0.22084210985859806
          },
          "params_rmse": {
            "mean": 1.7279388060172398,
            "std": 0.2895819950527343
          }
        },
        "30": {
          "delta_mid_rmse": {
            "mean": 0.00021942037043724363,
            "std": 9.923426306777983e-05
          },
          "log_spread_rmse": {
            "mean": 0.6632894563178221,
            "std": 0.186166597725504
          },
          "params_mae": {
            "mean": 1.1527160331606865,
            "std": 0.21919578205666773
          },
          "params_rmse": {
            "mean": 1.697539582848549,
            "std": 0.29027879412752117
          }
        }
      },
      "timing": {
        "horizon": {
          "mean": 30.0,
          "std": 0.0
        },
        "latency_ms_per_sample": {
          "mean": 683.8586687420806,
          "std": 0.6677174340056111
        },
        "latency_ms_per_step": {
          "mean": 22.795288958069353,
          "std": 0.022257247800186997
        },
        "latency_s_total": {
          "mean": 0.6838586687420806,
          "std": 0.0006677174340056111
        },
        "nfe": {
          "mean": 4.0,
          "std": 0.0
        },
        "throughput_steps_per_s": {
          "mean": 43.86875525708143,
          "std": 0.04278681894822911
        }
      },
      "meta": {
        "n_windows": 24,
        "nfe": 4,
        "horizon": 30
      }
    },
    "60": {
      "gen": {
        "depth_mean": {
          "mean": 533.2353439331055,
          "std": 68.29246266052229
        },
        "imb_mean": {
          "mean": -0.03668551230415081,
          "std": 0.05405234632661348
        },
        "imb_std": {
          "mean": 0.4464346158007781,
          "std": 0.05927450987222146
        },
        "spread_mean": {
          "mean": 0.0005928840922327557,
          "std": 0.00010582649626013762
        },
        "spread_std": {
          "mean": 0.00028866609864053316,
          "std": 5.718165270479235e-05
        }
      },
      "true": {
        "depth_mean": {
          "mean": 579.2611083984375,
          "std": 243.73573870086014
        },
        "imb_mean": {
          "mean": 0.0018569398671388626,
          "std": 0.13720963897709262
        },
        "imb_std": {
          "mean": 0.4187566662828128,
          "std": 0.0844272053492529
        },
        "spread_mean": {
          "mean": 0.0006882810739625711,
          "std": 0.0002714173017548798
        },
        "spread_std": {
          "mean": 0.0002095215965406775,
          "std": 0.00010956874428936067
        }
      },
      "cmp": {
        "basic_gen": {
          "depth_mean": {
            "mean": 533.2353439331055,
            "std": 68.29246266052229
          },
          "imb_mean": {
            "mean": -0.03668551230415081,
            "std": 0.05405234632661348
          },
          "imb_std": {
            "mean": 0.4464346158007781,
            "std": 0.05927450987222146
          },
          "spread_mean": {
            "mean": 0.0005928840922327557,
            "std": 0.00010582649626013762
          },
          "spread_std": {
            "mean": 0.00028866609864053316,
            "std": 5.718165270479235e-05
          }
        },
        "basic_true": {
          "depth_mean": {
            "mean": 579.2611083984375,
            "std": 243.73573870086014
          },
          "imb_mean": {
            "mean": 0.0018569398671388626,
            "std": 0.13720963897709262
          },
          "imb_std": {
            "mean": 0.4187566662828128,
            "std": 0.0844272053492529
          },
          "spread_mean": {
            "mean": 0.0006882810739625711,
            "std": 0.0002714173017548798
          },
          "spread_std": {
            "mean": 0.0002095215965406775,
            "std": 0.00010956874428936067
          }
        },
        "dist": {
          "depth": {
            "ks": {
              "mean": 0.32430555555555557,
              "std": 0.18874458335781075
            },
            "w1": {
              "mean": 189.94105206464175,
              "std": 145.37203547615465
            }
          },
          "imb": {
            "ks": {
              "mean": 0.2340277777777778,
              "std": 0.06879908461026117
            },
            "w1": {
              "mean": 0.15824313403424456,
              "std": 0.05866646088016066
            }
          },
          "ret": {
            "ks": {
              "mean": 0.2881944444444444,
              "std": 0.0725652909497184
            },
            "w1": {
              "mean": 5.7279129547101485e-05,
              "std": 2.5394863986226893e-05
            }
          },
          "spread": {
            "ks": {
              "mean": 0.3909722222222222,
              "std": 0.17407022626755989
            },
            "w1": {
              "mean": 0.00020779287097630675,
              "std": 0.0001518270143996536
            }
          }
        },
        "error": {
          "imbalance_mae": {
            "mean": 1.2818327270766836,
            "std": 0.19554373923910992
          },
          "spread_mae": {
            "mean": 1.7132072740485047,
            "std": 0.5331036932966707
          }
        },
        "microstructure": {
          "impact_response_curve_gen": {
            "1": {
              "mean": 4.726836849621523e-06,
              "std": 9.082462071017742e-06
            },
            "10": {
              "mean": -4.8041904307474895e-06,
              "std": 4.698421164737219e-05
            },
            "20": {
              "mean": -5.013893005081709e-06,
              "std": 6.007725394198219e-05
            },
            "5": {
              "mean": -1.1019198018220035e-06,
              "std": 3.5524638444110256e-05
            }
          },
          "impact_response_curve_true": {
            "1": {
              "mean": 1.2926898034641568e-05,
              "std": 1.6546392439748948e-05
            },
            "10": {
              "mean": 3.5519204650850652e-06,
              "std": 6.421565251286474e-05
            },
            "20": {
              "mean": 7.173499136335743e-06,
              "std": 0.00012296933262936772
            },
            "5": {
              "mean": 1.977782458877277e-05,
              "std": 4.240441754804756e-05
            }
          },
          "impact_response_l1": {
            "mean": 3.305982984044695,
            "std": 5.635590057776562
          }
        },
        "params_fit": {
          "delta_mid_rmse": {
            "mean": 0.00025150590893948294,
            "std": 9.071243067816325e-05
          },
          "log_spread_rmse": {
            "mean": 0.6757192003230253,
            "std": 0.12935691799986648
          },
          "params_mae": {
            "mean": 1.11636928965648,
            "std": 0.20474591953958454
          },
          "params_rmse": {
            "mean": 1.6509705285231273,
            "std": 0.24378550890932946
          }
        },
        "score_main": {
          "mean": 0.3268378199537367,
          "std": 0.0
        },
        "structure": {
          "vol_corr_mae": {
            "mean": 0.1502216303497841,
            "std": 0.04108120482477731
          },
          "vol_corr_rmse": {
            "mean": 0.20900015355869805,
            "std": 0.05093181413977528
          }
        },
        "temporal": {
          "depth": {
            "acf_l1": {
              "mean": 0.22850868927053258,
              "std": 0.08696404712532994
            },
            "acf_l2": {
              "mean": 0.2742205939012291,
              "std": 0.09202671161362558
            }
          },
          "imb": {
            "acf_l1": {
              "mean": 0.23057373433384812,
              "std": 0.04579172643650663
            },
            "acf_l2": {
              "mean": 0.27661157711918105,
              "std": 0.05228965512847343
            }
          },
          "ret": {
            "acf_l1": {
              "mean": 0.13606306251172587,
              "std": 0.02292468737593409
            },
            "acf_l2": {
              "mean": 0.17150329982652082,
              "std": 0.02981933294218781
            }
          },
          "spread": {
            "acf_l1": {
              "mean": 0.21625143429411922,
              "std": 0.08530160815071364
            },
            "acf_l2": {
              "mean": 0.25480029025046863,
              "std": 0.09973943860757288
            }
          },
          "volatility": {
            "acf_l1": {
              "mean": 0.23095592711265842,
              "std": 0.11279233426325014
            },
            "acf_l2": {
              "mean": 0.2707725622377612,
              "std": 0.13167475609560567
            }
          }
        },
        "validity": {
          "ask_monotonic_violation_rate": {
            "mean": 0.0,
            "std": 0.0
          },
          "bid_monotonic_violation_rate": {
            "mean": 0.0,
            "std": 0.0
          },
          "crossed_rate": {
            "mean": 0.0,
            "std": 0.0
          },
          "nonpositive_volume_rate": {
            "mean": 0.0,
            "std": 0.0
          },
          "valid_rate": {
            "mean": 1.0,
            "std": 0.0
          }
        },
        "main": {
          "tstr_macro_f1": {
            "mean": 0.3102177125137669,
            "std": 0.0
          },
          "disc_auc": {
            "mean": 0.6236080914083306,
            "std": 0.0
          },
          "disc_auc_gap": {
            "mean": 0.12360809140833062,
            "std": 0.0
          },
          "unconditional_w1": {
            "mean": 0.15309761599752056,
            "std": 0.0
          },
          "conditional_w1": {
            "mean": 0.4212105388557225,
            "std": 0.0
          },
          "label_horizon": 6,
          "n_examples_real": 1296,
          "n_examples_gen": 1296,
          "threshold_abs_move": {
            "mean": 9.759267413755879e-05,
            "std": 0.0
          },
          "unconditional_w1_by_stat": {
            "spread": {
              "mean": 0.2645268723404943,
              "std": 0.0
            },
            "depth": {
              "mean": 0.12455589663553765,
              "std": 0.0
            },
            "imb": {
              "mean": 0.09072444244434671,
              "std": 0.0
            },
            "ret": {
              "mean": 0.13258325256970346,
              "std": 0.0
            }
          },
          "conditional_w1_by_stat": {
            "spread": {
              "mean": 0.575665621674375,
              "std": 0.0
            },
            "depth": {
              "mean": 0.44648040780951503,
              "std": 0.0
            },
            "imb": {
              "mean": 0.35268706242704845,
              "std": 0.0
            },
            "ret": {
              "mean": 0.3100090635119517,
              "std": 0.0
            }
          },
          "stat_scales": {
            "spread": {
              "mean": 0.00036096105647567177,
              "std": 0.0
            },
            "depth": {
              "mean": 425.4185597896999,
              "std": 0.0
            },
            "imb": {
              "mean": 0.44867859043447716,
              "std": 0.0
            },
            "ret": {
              "mean": 0.0001847659836077445,
              "std": 0.0
            }
          }
        },
        "extra": {
          "u_l1": {
            "mean": 0.3572916666666667,
            "std": 0.0
          },
          "c_l1": {
            "mean": 1.423600028376568,
            "std": 0.0
          },
          "spread_specific_error": {
            "mean": 1.7132072740485047,
            "std": 0.5331036932966707
          },
          "imbalance_specific_error": {
            "mean": 1.2818327270766836,
            "std": 0.19554373923910992
          },
          "ret_vol_acf_error": {
            "mean": 0.18350949481219214,
            "std": 0.0
          },
          "impact_response_error": {
            "mean": 3.305982984044695,
            "std": 5.635590057776562
          },
          "efficiency_ms_per_sample": {
            "mean": 1369.0197130975623,
            "std": 1.318376429733604
          }
        },
        "legacy_score_main": {
          "mean": 1.9455417970696214,
          "std": 0.23773437050779825
        }
      },
      "horizon": {
        "10": {
          "delta_mid_rmse": {
            "mean": 0.00024472463580120046,
            "std": 0.00012590964172517357
          },
          "log_spread_rmse": {
            "mean": 0.5834514672557513,
            "std": 0.19612253498972235
          },
          "params_mae": {
            "mean": 1.045832912127177,
            "std": 0.2199209374976001
          },
          "params_rmse": {
            "mean": 1.5559311360120773,
            "std": 0.27926278138172955
          }
        },
        "30": {
          "delta_mid_rmse": {
            "mean": 0.00024101075541693717,
            "std": 8.779531037406302e-05
          },
          "log_spread_rmse": {
            "mean": 0.6665443107485771,
            "std": 0.16447192184951312
          },
          "params_mae": {
            "mean": 1.0946503604451816,
            "std": 0.201928042180837
          },
          "params_rmse": {
            "mean": 1.6191204190254211,
            "std": 0.24068187827384388
          }
        },
        "60": {
          "delta_mid_rmse": {
            "mean": 0.00025150590893948294,
            "std": 9.071243067816325e-05
          },
          "log_spread_rmse": {
            "mean": 0.6757192003230253,
            "std": 0.12935691799986648
          },
          "params_mae": {
            "mean": 1.11636928965648,
            "std": 0.20474591953958454
          },
          "params_rmse": {
            "mean": 1.6509705285231273,
            "std": 0.24378550890932946
          }
        }
      },
      "timing": {
        "horizon": {
          "mean": 60.0,
          "std": 0.0
        },
        "latency_ms_per_sample": {
          "mean": 1369.0197130975623,
          "std": 1.318376429733604
        },
        "latency_ms_per_step": {
          "mean": 22.816995218292707,
          "std": 0.021972940495559864
        },
        "latency_s_total": {
          "mean": 1.3690197130975623,
          "std": 0.0013183764297336042
        },
        "nfe": {
          "mean": 4.0,
          "std": 0.0
        },
        "throughput_steps_per_s": {
          "mean": 43.82702095832361,
          "std": 0.04221731164268219
        }
      },
      "meta": {
        "n_windows": 24,
        "nfe": 4,
        "horizon": 60
      }
    }
  }
}
