{
  "row": {
    "variant": "baseline_fm",
    "seed": 2,
    "checkpoint": 4000,
    "score_main": 0.39922543302249397,
    "tstr_macro_f1": 0.3480533081965454,
    "disc_auc_gap": 0.4505721440853594,
    "unconditional_w1": 0.2532869247188208,
    "conditional_w1": 0.3083909492822463,
    "train_seconds": 630.0458650588989,
    "eval_seconds": 170.29840350151062
  },
  "result": {
    "32": {
      "gen": {
        "depth_mean": {
          "mean": 166210.90059407553,
          "std": 105337.02202580046
        },
        "imb_mean": {
          "mean": 0.03993368668792149,
          "std": 0.014846445642905041
        },
        "imb_std": {
          "mean": 0.10726688615977764,
          "std": 0.037455413108368994
        },
        "spread_mean": {
          "mean": 0.04691080252329508,
          "std": 0.05750489327858145
        },
        "spread_std": {
          "mean": 0.020167320370092057,
          "std": 0.03242548266310704
        }
      },
      "true": {
        "depth_mean": {
          "mean": 216473.41243489584,
          "std": 141931.61314371153
        },
        "imb_mean": {
          "mean": 0.032423762837424874,
          "std": 0.21389003126490297
        },
        "imb_std": {
          "mean": 0.10521917665998141,
          "std": 0.06426496328662262
        },
        "spread_mean": {
          "mean": 0.05206612745920817,
          "std": 0.08551481100187709
        },
        "spread_std": {
          "mean": 0.01748630227268677,
          "std": 0.038611799126370035
        }
      },
      "cmp": {
        "basic_gen": {
          "depth_mean": {
            "mean": 166210.90059407553,
            "std": 105337.02202580046
          },
          "imb_mean": {
            "mean": 0.03993368668792149,
            "std": 0.014846445642905041
          },
          "imb_std": {
            "mean": 0.10726688615977764,
            "std": 0.037455413108368994
          },
          "spread_mean": {
            "mean": 0.04691080252329508,
            "std": 0.05750489327858145
          },
          "spread_std": {
            "mean": 0.020167320370092057,
            "std": 0.03242548266310704
          }
        },
        "basic_true": {
          "depth_mean": {
            "mean": 216473.41243489584,
            "std": 141931.61314371153
          },
          "imb_mean": {
            "mean": 0.032423762837424874,
            "std": 0.21389003126490297
          },
          "imb_std": {
            "mean": 0.10521917665998141,
            "std": 0.06426496328662262
          },
          "spread_mean": {
            "mean": 0.05206612745920817,
            "std": 0.08551481100187709
          },
          "spread_std": {
            "mean": 0.01748630227268677,
            "std": 0.038611799126370035
          }
        },
        "dist": {
          "depth": {
            "ks": {
              "mean": 0.8111979166666666,
              "std": 0.18142932191304245
            },
            "w1": {
              "mean": 50397.95336274306,
              "std": 48540.248066249915
            }
          },
          "imb": {
            "ks": {
              "mean": 0.5416666666666666,
              "std": 0.2756483046333175
            },
            "w1": {
              "mean": 0.15488806278388934,
              "std": 0.15890448615469385
            }
          },
          "ret": {
            "ks": {
              "mean": 0.4283854166666667,
              "std": 0.23704712281139317
            },
            "w1": {
              "mean": 0.0008819478874405225,
              "std": 0.000983370050238808
            }
          },
          "spread": {
            "ks": {
              "mean": 0.6640625,
              "std": 0.22719022235874647
            },
            "w1": {
              "mean": 0.017900758733352024,
              "std": 0.04300912687990657
            }
          }
        },
        "error": {
          "imbalance_mae": {
            "mean": 2.118311387127186,
            "std": 1.2413325283311676
          },
          "spread_mae": {
            "mean": 712.0218513788159,
            "std": 811.9268055893266
          }
        },
        "microstructure": {
          "impact_response_curve_gen": {
            "1": {
              "mean": 3.143319033616595e-05,
              "std": 9.632070830734703e-05
            },
            "10": {
              "mean": -9.127965481257084e-05,
              "std": 0.00025662216951906076
            },
            "20": {
              "mean": -0.00021329648357500737,
              "std": 0.0005607419843796586
            },
            "5": {
              "mean": 1.6386109052410723e-05,
              "std": 0.00017788350468370953
            }
          },
          "impact_response_curve_true": {
            "1": {
              "mean": -8.115678156225676e-05,
              "std": 0.0003321879032373296
            },
            "10": {
              "mean": -0.0014477948506795466,
              "std": 0.004917531705828969
            },
            "20": {
              "mean": -0.0020623100279051135,
              "std": 0.0078119560895359135
            },
            "5": {
              "mean": -0.0006923213239576847,
              "std": 0.0023334034819470226
            }
          },
          "impact_response_l1": {
            "mean": 1.3880230033844405,
            "std": 0.8588482925008524
          }
        },
        "params_fit": {
          "delta_mid_rmse": {
            "mean": 0.003509687286471793,
            "std": 0.005207389778699479
          },
          "log_spread_rmse": {
            "mean": 0.37734211546679336,
            "std": 0.23075933603312399
          },
          "params_mae": {
            "mean": 0.4604568878809611,
            "std": 0.2602287434955947
          },
          "params_rmse": {
            "mean": 0.6945594226320585,
            "std": 0.2940844677963285
          }
        },
        "score_main": {
          "mean": 0.3900667519639983,
          "std": 0.0
        },
        "structure": {
          "vol_corr_mae": {
            "mean": 0.37871414842091955,
            "std": 0.028556402050024965
          },
          "vol_corr_rmse": {
            "mean": 0.46382833690391506,
            "std": 0.031795822067685074
          }
        },
        "temporal": {
          "depth": {
            "acf_l1": {
              "mean": 0.3637127299842678,
              "std": 0.10552414112662284
            },
            "acf_l2": {
              "mean": 0.4433325276707425,
              "std": 0.11956884086450026
            }
          },
          "imb": {
            "acf_l1": {
              "mean": 0.4217844507135153,
              "std": 0.11139695099222309
            },
            "acf_l2": {
              "mean": 0.5017678074604025,
              "std": 0.11789675408500917
            }
          },
          "ret": {
            "acf_l1": {
              "mean": 0.286874252256808,
              "std": 0.10430998657601594
            },
            "acf_l2": {
              "mean": 0.3514502932917128,
              "std": 0.11805038099748262
            }
          },
          "spread": {
            "acf_l1": {
              "mean": 0.2626634529923004,
              "std": 0.12226655596363892
            },
            "acf_l2": {
              "mean": 0.3245338162394829,
              "std": 0.13648548752293574
            }
          },
          "volatility": {
            "acf_l1": {
              "mean": 0.27779616561197223,
              "std": 0.1271286194600342
            },
            "acf_l2": {
              "mean": 0.328055373061689,
              "std": 0.14172741985425422
            }
          }
        },
        "validity": {
          "ask_monotonic_violation_rate": {
            "mean": 0.0,
            "std": 0.0
          },
          "bid_monotonic_violation_rate": {
            "mean": 0.0,
            "std": 0.0
          },
          "crossed_rate": {
            "mean": 0.0,
            "std": 0.0
          },
          "nonpositive_volume_rate": {
            "mean": 0.0,
            "std": 0.0
          },
          "valid_rate": {
            "mean": 1.0,
            "std": 0.0
          }
        },
        "main": {
          "tstr_macro_f1": {
            "mean": 0.3526300133214346,
            "std": 0.0
          },
          "disc_auc": {
            "mean": 0.9163938554520272,
            "std": 0.0
          },
          "disc_auc_gap": {
            "mean": 0.41639385545202723,
            "std": 0.0
          },
          "unconditional_w1": {
            "mean": 0.23424829376352704,
            "std": 0.0
          },
          "conditional_w1": {
            "mean": 0.3311470976885379,
            "std": 0.0
          },
          "label_horizon": 3,
          "n_examples_real": 696,
          "n_examples_gen": 696,
          "threshold_abs_move": {
            "mean": 0.000732421875,
            "std": 0.0
          },
          "unconditional_w1_by_stat": {
            "spread": {
              "mean": 0.1046483486200165,
              "std": 0.0
            },
            "depth": {
              "mean": 0.3488151505703875,
              "std": 0.0
            },
            "imb": {
              "mean": 0.3970535922925637,
              "std": 0.0
            },
            "ret": {
              "mean": 0.08647608357114056,
              "std": 0.0
            }
          },
          "conditional_w1_by_stat": {
            "spread": {
              "mean": 0.1875518773040125,
              "std": 0.0
            },
            "depth": {
              "mean": 0.3505896777947565,
              "std": 0.0
            },
            "imb": {
              "mean": 0.6273780368082723,
              "std": 0.0
            },
            "ret": {
              "mean": 0.15906879884711034,
              "std": 0.0
            }
          },
          "stat_scales": {
            "spread": {
              "mean": 0.09544430581377633,
              "std": 0.0
            },
            "depth": {
              "mean": 143751.96006839428,
              "std": 0.0
            },
            "imb": {
              "mean": 0.24688155098936523,
              "std": 0.0
            },
            "ret": {
              "mean": 0.005544442994683141,
              "std": 0.0
            }
          }
        },
        "extra": {
          "u_l1": {
            "mean": 0.5,
            "std": 0.0
          },
          "c_l1": {
            "mean": 179.7590902134445,
            "std": 0.0
          },
          "spread_specific_error": {
            "mean": 712.0218513788159,
            "std": 811.9268055893266
          },
          "imbalance_specific_error": {
            "mean": 2.118311387127186,
            "std": 1.2413325283311676
          },
          "ret_vol_acf_error": {
            "mean": 0.2823352089343901,
            "std": 0.0
          },
          "impact_response_error": {
            "mean": 1.3880230033844405,
            "std": 0.8588482925008524
          },
          "efficiency_ms_per_sample": {
            "mean": 333.9009100648885,
            "std": 0.5010297910183562
          }
        },
        "legacy_score_main": {
          "mean": 1.1551044442935483,
          "std": 0.4047036536862484
        }
      },
      "horizon": {
        "32": {
          "delta_mid_rmse": {
            "mean": 0.003509687286471793,
            "std": 0.005207389778699479
          },
          "log_spread_rmse": {
            "mean": 0.37734211546679336,
            "std": 0.23075933603312399
          },
          "params_mae": {
            "mean": 0.4604568878809611,
            "std": 0.2602287434955947
          },
          "params_rmse": {
            "mean": 0.6945594226320585,
            "std": 0.2940844677963285
          }
        }
      },
      "timing": {
        "horizon": {
          "mean": 32.0,
          "std": 0.0
        },
        "latency_ms_per_sample": {
          "mean": 333.9009100648885,
          "std": 0.5010297910183562
        },
        "latency_ms_per_step": {
          "mean": 10.434403439527765,
          "std": 0.01565718096932363
        },
        "latency_s_total": {
          "mean": 0.3339009100648885,
          "std": 0.0005010297910183561
        },
        "nfe": {
          "mean": 2.0,
          "std": 0.0
        },
        "throughput_steps_per_s": {
          "mean": 95.83703121054585,
          "std": 0.14358346661916432
        }
      },
      "meta": {
        "n_windows": 24,
        "nfe": 2,
        "horizon": 32
      }
    },
    "128": {
      "gen": {
        "depth_mean": {
          "mean": 165896.44841512045,
          "std": 104423.74720801342
        },
        "imb_mean": {
          "mean": 0.04363713535713032,
          "std": 0.015178977351739913
        },
        "imb_std": {
          "mean": 0.11355115224917729,
          "std": 0.03926174533909679
        },
        "spread_mean": {
          "mean": 0.040221999088923134,
          "std": 0.04601104130890942
        },
        "spread_std": {
          "mean": 0.015240509902165892,
          "std": 0.02155561675480949
        }
      },
      "true": {
        "depth_mean": {
          "mean": 217586.26135253906,
          "std": 140716.16782011354
        },
        "imb_mean": {
          "mean": 0.02050140377347513,
          "std": 0.14748352296749964
        },
        "imb_std": {
          "mean": 0.15303464078654846,
          "std": 0.07811639150915928
        },
        "spread_mean": {
          "mean": 0.054549574851989746,
          "std": 0.08311526197846308
        },
        "spread_std": {
          "mean": 0.02458112028883382,
          "std": 0.04570163543350639
        }
      },
      "cmp": {
        "basic_gen": {
          "depth_mean": {
            "mean": 165896.44841512045,
            "std": 104423.74720801342
          },
          "imb_mean": {
            "mean": 0.04363713535713032,
            "std": 0.015178977351739913
          },
          "imb_std": {
            "mean": 0.11355115224917729,
            "std": 0.03926174533909679
          },
          "spread_mean": {
            "mean": 0.040221999088923134,
            "std": 0.04601104130890942
          },
          "spread_std": {
            "mean": 0.015240509902165892,
            "std": 0.02155561675480949
          }
        },
        "basic_true": {
          "depth_mean": {
            "mean": 217586.26135253906,
            "std": 140716.16782011354
          },
          "imb_mean": {
            "mean": 0.02050140377347513,
            "std": 0.14748352296749964
          },
          "imb_std": {
            "mean": 0.15303464078654846,
            "std": 0.07811639150915928
          },
          "spread_mean": {
            "mean": 0.054549574851989746,
            "std": 0.08311526197846308
          },
          "spread_std": {
            "mean": 0.02458112028883382,
            "std": 0.04570163543350639
          }
        },
        "dist": {
          "depth": {
            "ks": {
              "mean": 0.6357421875,
              "std": 0.25373404116001447
            },
            "w1": {
              "mean": 51711.009195426166,
              "std": 44308.15903388747
            }
          },
          "imb": {
            "ks": {
              "mean": 0.3623046875,
              "std": 0.20442060391469902
            },
            "w1": {
              "mean": 0.11818515139380874,
              "std": 0.10602429078883994
            }
          },
          "ret": {
            "ks": {
              "mean": 0.2470703125,
              "std": 0.14406972518091518
            },
            "w1": {
              "mean": 0.0009519717423245311,
              "std": 0.0012408408101071463
            }
          },
          "spread": {
            "ks": {
              "mean": 0.5709635416666666,
              "std": 0.20761901465499438
            },
            "w1": {
              "mean": 0.01732790652507295,
              "std": 0.043964820552273784
            }
          }
        },
        "error": {
          "imbalance_mae": {
            "mean": 1.280709140335365,
            "std": 0.3446838611895795
          },
          "spread_mae": {
            "mean": 214.06665228963843,
            "std": 564.2770281584446
          }
        },
        "microstructure": {
          "impact_response_curve_gen": {
            "1": {
              "mean": -1.3012991118712516e-05,
              "std": 3.592359816457286e-05
            },
            "10": {
              "mean": -0.00012713778133690025,
              "std": 0.00023674833639933713
            },
            "20": {
              "mean": -0.0002346218662698439,
              "std": 0.00045954978599875725
            },
            "5": {
              "mean": -5.129263887196876e-05,
              "std": 0.00012204836927516196
            }
          },
          "impact_response_curve_true": {
            "1": {
              "mean": -1.9969186994005493e-05,
              "std": 0.00023679654443512874
            },
            "10": {
              "mean": -0.0002879624713703784,
              "std": 0.0018632753758795403
            },
            "20": {
              "mean": -0.0005348432375779012,
              "std": 0.0032513340213562334
            },
            "5": {
              "mean": -0.00016077905587670195,
              "std": 0.001042838041247317
            }
          },
          "impact_response_l1": {
            "mean": 1.3598419386232585,
            "std": 1.0182613515628758
          }
        },
        "params_fit": {
          "delta_mid_rmse": {
            "mean": 0.003955064959882293,
            "std": 0.005526159937412294
          },
          "log_spread_rmse": {
            "mean": 0.3987996106346448,
            "std": 0.24340773100559568
          },
          "params_mae": {
            "mean": 0.4707353363434474,
            "std": 0.2605301073303008
          },
          "params_rmse": {
            "mean": 0.7161122336983681,
            "std": 0.297843385661672
          }
        },
        "score_main": {
          "mean": 0.39340297195173984,
          "std": 0.0
        },
        "structure": {
          "vol_corr_mae": {
            "mean": 0.28705416224695196,
            "std": 0.024591634687394247
          },
          "vol_corr_rmse": {
            "mean": 0.3542066328497631,
            "std": 0.02644400038018805
          }
        },
        "temporal": {
          "depth": {
            "acf_l1": {
              "mean": 0.32084366870381265,
              "std": 0.12120640118242539
            },
            "acf_l2": {
              "mean": 0.3534830489750858,
              "std": 0.12012091224253278
            }
          },
          "imb": {
            "acf_l1": {
              "mean": 0.45590281534897276,
              "std": 0.1295414036407737
            },
            "acf_l2": {
              "mean": 0.5200162593039207,
              "std": 0.10848362411407225
            }
          },
          "ret": {
            "acf_l1": {
              "mean": 0.33652129939691083,
              "std": 0.1983314970764193
            },
            "acf_l2": {
              "mean": 0.37457723174945845,
              "std": 0.19730750503495673
            }
          },
          "spread": {
            "acf_l1": {
              "mean": 0.2522975146834095,
              "std": 0.17319444298221254
            },
            "acf_l2": {
              "mean": 0.30380410265023206,
              "std": 0.1815935107359045
            }
          },
          "volatility": {
            "acf_l1": {
              "mean": 0.1808308888110365,
              "std": 0.08895762331445906
            },
            "acf_l2": {
              "mean": 0.20960003898760685,
              "std": 0.0943796004122666
            }
          }
        },
        "validity": {
          "ask_monotonic_violation_rate": {
            "mean": 0.0,
            "std": 0.0
          },
          "bid_monotonic_violation_rate": {
            "mean": 0.0,
            "std": 0.0
          },
          "crossed_rate": {
            "mean": 0.0,
            "std": 0.0
          },
          "nonpositive_volume_rate": {
            "mean": 0.0,
            "std": 0.0
          },
          "valid_rate": {
            "mean": 1.0,
            "std": 0.0
          }
        },
        "main": {
          "tstr_macro_f1": {
            "mean": 0.35453154171504037,
            "std": 0.0
          },
          "disc_auc": {
            "mean": 0.9419321799307958,
            "std": 0.0
          },
          "disc_auc_gap": {
            "mean": 0.4419321799307958,
            "std": 0.0
          },
          "unconditional_w1": {
            "mean": 0.24814750529807375,
            "std": 0.0
          },
          "conditional_w1": {
            "mean": 0.30284559731337457,
            "std": 0.0
          },
          "label_horizon": 10,
          "n_examples_real": 2832,
          "n_examples_gen": 2832,
          "threshold_abs_move": {
            "mean": 0.002105712890625,
            "std": 0.0
          },
          "unconditional_w1_by_stat": {
            "spread": {
              "mean": 0.1578158130239336,
              "std": 0.0
            },
            "depth": {
              "mean": 0.35875906613962355,
              "std": 0.0
            },
            "imb": {
              "mean": 0.3460280310204441,
              "std": 0.0
            },
            "ret": {
              "mean": 0.12998711100829377,
              "std": 0.0
            }
          },
          "conditional_w1_by_stat": {
            "spread": {
              "mean": 0.17684102730374057,
              "std": 0.0
            },
            "depth": {
              "mean": 0.3590476969566549,
              "std": 0.0
            },
            "imb": {
              "mean": 0.5219344323310104,
              "std": 0.0
            },
            "ret": {
              "mean": 0.15355923266209218,
              "std": 0.0
            }
          },
          "stat_scales": {
            "spread": {
              "mean": 0.09798578298977359,
              "std": 0.0
            },
            "depth": {
              "mean": 144022.67340449992,
              "std": 0.0
            },
            "imb": {
              "mean": 0.2264367784014215,
              "std": 0.0
            },
            "ret": {
              "mean": 0.006199378088970719,
              "std": 0.0
            }
          }
        },
        "extra": {
          "u_l1": {
            "mean": 0.44075520833333337,
            "std": 0.0
          },
          "c_l1": {
            "mean": 54.64141876922283,
            "std": 0.0
          },
          "spread_specific_error": {
            "mean": 214.06665228963843,
            "std": 564.2770281584446
          },
          "imbalance_specific_error": {
            "mean": 1.280709140335365,
            "std": 0.3446838611895795
          },
          "ret_vol_acf_error": {
            "mean": 0.2586760941039737,
            "std": 0.0
          },
          "impact_response_error": {
            "mean": 1.3598419386232585,
            "std": 1.0182613515628758
          },
          "efficiency_ms_per_sample": {
            "mean": 1335.4104064637795,
            "std": 1.4473576952797993
          }
        },
        "legacy_score_main": {
          "mean": 1.1890985627564852,
          "std": 0.2789035079161722
        }
      },
      "horizon": {
        "128": {
          "delta_mid_rmse": {
            "mean": 0.003955064959882293,
            "std": 0.005526159937412294
          },
          "log_spread_rmse": {
            "mean": 0.3987996106346448,
            "std": 0.24340773100559568
          },
          "params_mae": {
            "mean": 0.4707353363434474,
            "std": 0.2605301073303008
          },
          "params_rmse": {
            "mean": 0.7161122336983681,
            "std": 0.297843385661672
          }
        },
        "32": {
          "delta_mid_rmse": {
            "mean": 0.0039058073173994976,
            "std": 0.005699772162318968
          },
          "log_spread_rmse": {
            "mean": 0.4234814240286748,
            "std": 0.25294501097940725
          },
          "params_mae": {
            "mean": 0.45884618535637856,
            "std": 0.256804566391623
          },
          "params_rmse": {
            "mean": 0.6962246658901373,
            "std": 0.29894887900377937
          }
        }
      },
      "timing": {
        "horizon": {
          "mean": 128.0,
          "std": 0.0
        },
        "latency_ms_per_sample": {
          "mean": 1335.4104064637795,
          "std": 1.4473576952797993
        },
        "latency_ms_per_step": {
          "mean": 10.432893800498277,
          "std": 0.011307481994373432
        },
        "latency_s_total": {
          "mean": 1.3354104064637795,
          "std": 0.0014473576952797993
        },
        "nfe": {
          "mean": 2.0,
          "std": 0.0
        },
        "throughput_steps_per_s": {
          "mean": 95.85079591838706,
          "std": 0.10387025551146126
        }
      },
      "meta": {
        "n_windows": 24,
        "nfe": 2,
        "horizon": 128
      }
    },
    "512": {
      "gen": {
        "depth_mean": {
          "mean": 163171.85018920898,
          "std": 102145.6427507977
        },
        "imb_mean": {
          "mean": 0.0482889188763996,
          "std": 0.011154088093496797
        },
        "imb_std": {
          "mean": 0.11471295574059089,
          "std": 0.03533156968594892
        },
        "spread_mean": {
          "mean": 0.0359334001938502,
          "std": 0.038410635789505605
        },
        "spread_std": {
          "mean": 0.01521004829070686,
          "std": 0.022935589422619092
        }
      },
      "true": {
        "depth_mean": {
          "mean": 218175.76790364584,
          "std": 138587.55522818887
        },
        "imb_mean": {
          "mean": 0.03995251023055365,
          "std": 0.072239184568211
        },
        "imb_std": {
          "mean": 0.19872593227773905,
          "std": 0.07170762523733351
        },
        "spread_mean": {
          "mean": 0.05485298981269201,
          "std": 0.07461258184653385
        },
        "spread_std": {
          "mean": 0.029229660955024883,
          "std": 0.0444717557998422
        }
      },
      "cmp": {
        "basic_gen": {
          "depth_mean": {
            "mean": 163171.85018920898,
            "std": 102145.6427507977
          },
          "imb_mean": {
            "mean": 0.0482889188763996,
            "std": 0.011154088093496797
          },
          "imb_std": {
            "mean": 0.11471295574059089,
            "std": 0.03533156968594892
          },
          "spread_mean": {
            "mean": 0.0359334001938502,
            "std": 0.038410635789505605
          },
          "spread_std": {
            "mean": 0.01521004829070686,
            "std": 0.022935589422619092
          }
        },
        "basic_true": {
          "depth_mean": {
            "mean": 218175.76790364584,
            "std": 138587.55522818887
          },
          "imb_mean": {
            "mean": 0.03995251023055365,
            "std": 0.072239184568211
          },
          "imb_std": {
            "mean": 0.19872593227773905,
            "std": 0.07170762523733351
          },
          "spread_mean": {
            "mean": 0.05485298981269201,
            "std": 0.07461258184653385
          },
          "spread_std": {
            "mean": 0.029229660955024883,
            "std": 0.0444717557998422
          }
        },
        "dist": {
          "depth": {
            "ks": {
              "mean": 0.593505859375,
              "std": 0.24495392690546247
            },
            "w1": {
              "mean": 55182.15300469054,
              "std": 38658.54107227801
            }
          },
          "imb": {
            "ks": {
              "mean": 0.24348958333333334,
              "std": 0.08325000411381422
            },
            "w1": {
              "mean": 0.08936825913794832,
              "std": 0.0510550458875109
            }
          },
          "ret": {
            "ks": {
              "mean": 0.18839518229166666,
              "std": 0.08870961585311518
            },
            "w1": {
              "mean": 0.0009620279852242675,
              "std": 0.001506727828916935
            }
          },
          "spread": {
            "ks": {
              "mean": 0.5030924479166666,
              "std": 0.156987716350853
            },
            "w1": {
              "mean": 0.020099546578421723,
              "std": 0.0410036967510742
            }
          }
        },
        "error": {
          "imbalance_mae": {
            "mean": 0.9792084421863345,
            "std": 0.05789673445883427
          },
          "spread_mae": {
            "mean": 76.2440915314879,
            "std": 361.5160980116699
          }
        },
        "microstructure": {
          "impact_response_curve_gen": {
            "1": {
              "mean": -1.6682377031234447e-05,
              "std": 2.059888997505153e-05
            },
            "10": {
              "mean": -0.00016729494093333398,
              "std": 0.00023639740869852598
            },
            "20": {
              "mean": -0.0003049262116263318,
              "std": 0.00042059569400133796
            },
            "5": {
              "mean": -8.772081606499135e-05,
              "std": 0.00011772927452074732
            }
          },
          "impact_response_curve_true": {
            "1": {
              "mean": 2.4701543437558174e-05,
              "std": 6.30901685528866e-05
            },
            "10": {
              "mean": 0.00023611747038706295,
              "std": 0.00043253554134780274
            },
            "20": {
              "mean": 0.0003120225677418482,
              "std": 0.0009944660212724483
            },
            "5": {
              "mean": 0.00011096549981542049,
              "std": 0.0002340206127317314
            }
          },
          "impact_response_l1": {
            "mean": 1.749899791580211,
            "std": 1.5388145046430326
          }
        },
        "params_fit": {
          "delta_mid_rmse": {
            "mean": 0.0037355041640694253,
            "std": 0.004966284241902675
          },
          "log_spread_rmse": {
            "mean": 0.45958970797558624,
            "std": 0.25980805157693804
          },
          "params_mae": {
            "mean": 0.483104158192873,
            "std": 0.27860797975062307
          },
          "params_rmse": {
            "mean": 0.7338398595650991,
            "std": 0.32089113151964965
          }
        },
        "score_main": {
          "mean": 0.41420657515174375,
          "std": 0.0
        },
        "structure": {
          "vol_corr_mae": {
            "mean": 0.17528988792685243,
            "std": 0.016235875414503595
          },
          "vol_corr_rmse": {
            "mean": 0.21927113240329454,
            "std": 0.019465833349883603
          }
        },
        "temporal": {
          "depth": {
            "acf_l1": {
              "mean": 0.45285804066939933,
              "std": 0.12713575676392572
            },
            "acf_l2": {
              "mean": 0.47279303429434605,
              "std": 0.11948443826656278
            }
          },
          "imb": {
            "acf_l1": {
              "mean": 0.6316974417753953,
              "std": 0.13248338747545874
            },
            "acf_l2": {
              "mean": 0.6623799148628184,
              "std": 0.10608993537699962
            }
          },
          "ret": {
            "acf_l1": {
              "mean": 0.5144714480628044,
              "std": 0.3082931760065141
            },
            "acf_l2": {
              "mean": 0.5251536403133262,
              "std": 0.3047393370519437
            }
          },
          "spread": {
            "acf_l1": {
              "mean": 0.48563414385585696,
              "std": 0.21971068629887183
            },
            "acf_l2": {
              "mean": 0.5159431883325769,
              "std": 0.20530978840025424
            }
          },
          "volatility": {
            "acf_l1": {
              "mean": 0.13016271369925436,
              "std": 0.06542968800866167
            },
            "acf_l2": {
              "mean": 0.14714564935202537,
              "std": 0.06797612250447162
            }
          }
        },
        "validity": {
          "ask_monotonic_violation_rate": {
            "mean": 0.0,
            "std": 0.0
          },
          "bid_monotonic_violation_rate": {
            "mean": 0.0,
            "std": 0.0
          },
          "crossed_rate": {
            "mean": 0.0,
            "std": 0.0
          },
          "nonpositive_volume_rate": {
            "mean": 0.0,
            "std": 0.0
          },
          "valid_rate": {
            "mean": 1.0,
            "std": 0.0
          }
        },
        "main": {
          "tstr_macro_f1": {
            "mean": 0.33699836955316137,
            "std": 0.0
          },
          "disc_auc": {
            "mean": 0.9933903968732553,
            "std": 0.0
          },
          "disc_auc_gap": {
            "mean": 0.49339039687325525,
            "std": 0.0
          },
          "unconditional_w1": {
            "mean": 0.2774649750948617,
            "std": 0.0
          },
          "conditional_w1": {
            "mean": 0.29118015284482646,
            "std": 0.0
          },
          "label_horizon": 10,
          "n_examples_real": 12048,
          "n_examples_gen": 12048,
          "threshold_abs_move": {
            "mean": 0.0028533935546875,
            "std": 0.0
          },
          "unconditional_w1_by_stat": {
            "spread": {
              "mean": 0.2176390069412681,
              "std": 0.0
            },
            "depth": {
              "mean": 0.3807451794831782,
              "std": 0.0
            },
            "imb": {
              "mean": 0.36132066450533323,
              "std": 0.0
            },
            "ret": {
              "mean": 0.15015504944966696,
              "std": 0.0
            }
          },
          "conditional_w1_by_stat": {
            "spread": {
              "mean": 0.21931276717053697,
              "std": 0.0
            },
            "depth": {
              "mean": 0.38062593291993385,
              "std": 0.0
            },
            "imb": {
              "mean": 0.40025610607211937,
              "std": 0.0
            },
            "ret": {
              "mean": 0.16452580521671575,
              "std": 0.0
            }
          },
          "stat_scales": {
            "spread": {
              "mean": 0.09164786363209021,
              "std": 0.0
            },
            "depth": {
              "mean": 144977.38654160046,
              "std": 0.0
            },
            "imb": {
              "mean": 0.22327769091384125,
              "std": 0.0
            },
            "ret": {
              "mean": 0.005847277173067595,
              "std": 0.0
            }
          }
        },
        "extra": {
          "u_l1": {
            "mean": 0.49755859374999994,
            "std": 0.0
          },
          "c_l1": {
            "mean": 19.943631102128023,
            "std": 0.0
          },
          "spread_specific_error": {
            "mean": 76.2440915314879,
            "std": 361.5160980116699
          },
          "imbalance_specific_error": {
            "mean": 0.9792084421863345,
            "std": 0.05789673445883427
          },
          "ret_vol_acf_error": {
            "mean": 0.3223170808810294,
            "std": 0.0
          },
          "impact_response_error": {
            "mean": 1.749899791580211,
            "std": 1.5388145046430326
          },
          "efficiency_ms_per_sample": {
            "mean": 5339.5981229453655,
            "std": 3.11033060447496
          }
        },
        "legacy_score_main": {
          "mean": 1.3587411413294979,
          "std": 0.162418449378209
        }
      },
      "horizon": {
        "128": {
          "delta_mid_rmse": {
            "mean": 0.0033895705831431164,
            "std": 0.004498936822542446
          },
          "log_spread_rmse": {
            "mean": 0.4538839093099038,
            "std": 0.2792082610852217
          },
          "params_mae": {
            "mean": 0.46658553058902424,
            "std": 0.25666372475044447
          },
          "params_rmse": {
            "mean": 0.7082534121970335,
            "std": 0.2926321849759224
          }
        },
        "32": {
          "delta_mid_rmse": {
            "mean": 0.0031468245530656227,
            "std": 0.004181371989723244
          },
          "log_spread_rmse": {
            "mean": 0.4439268298447132,
            "std": 0.2572567950456206
          },
          "params_mae": {
            "mean": 0.4550649436811606,
            "std": 0.2454462705045363
          },
          "params_rmse": {
            "mean": 0.6892085261642933,
            "std": 0.2762032958907673
          }
        },
        "512": {
          "delta_mid_rmse": {
            "mean": 0.0037355041640694253,
            "std": 0.004966284241902675
          },
          "log_spread_rmse": {
            "mean": 0.45958970797558624,
            "std": 0.25980805157693804
          },
          "params_mae": {
            "mean": 0.483104158192873,
            "std": 0.27860797975062307
          },
          "params_rmse": {
            "mean": 0.7338398595650991,
            "std": 0.32089113151964965
          }
        }
      },
      "timing": {
        "horizon": {
          "mean": 512.0,
          "std": 0.0
        },
        "latency_ms_per_sample": {
          "mean": 5339.5981229453655,
          "std": 3.11033060447496
        },
        "latency_ms_per_step": {
          "mean": 10.428902583877667,
          "std": 0.0060748644618651565
        },
        "latency_s_total": {
          "mean": 5.3395981229453655,
          "std": 0.0031103306044749607
        },
        "nfe": {
          "mean": 2.0,
          "std": 0.0
        },
        "throughput_steps_per_s": {
          "mean": 95.88739863190335,
          "std": 0.05586193439878687
        }
      },
      "meta": {
        "n_windows": 24,
        "nfe": 2,
        "horizon": 512
      }
    }
  }
}
