{
  "row": {
    "variant": "conditional_current_matching",
    "seed": 1,
    "checkpoint": 4000,
    "score_main": 0.3865628569903476,
    "tstr_macro_f1": 0.3935056536346704,
    "disc_auc_gap": 0.4243364786630237,
    "unconditional_w1": 0.26506042410049635,
    "conditional_w1": 0.3239340968554975,
    "train_seconds": 943.6171202659607,
    "eval_seconds": 171.0726261138916
  },
  "result": {
    "32": {
      "gen": {
        "depth_mean": {
          "mean": 110137.92635091145,
          "std": 116802.12986393065
        },
        "imb_mean": {
          "mean": 0.06228546922405561,
          "std": 0.05087179755935901
        },
        "imb_std": {
          "mean": 0.11578871278713147,
          "std": 0.029030843337315218
        },
        "spread_mean": {
          "mean": 0.06283239523569743,
          "std": 0.04771566533786083
        },
        "spread_std": {
          "mean": 0.021191804407862946,
          "std": 0.01867052859468154
        }
      },
      "true": {
        "depth_mean": {
          "mean": 138612.64161173502,
          "std": 148318.43541847734
        },
        "imb_mean": {
          "mean": 0.02967020500606547,
          "std": 0.17427951313694295
        },
        "imb_std": {
          "mean": 0.11398454895243049,
          "std": 0.056507245937748765
        },
        "spread_mean": {
          "mean": 0.07806722323099773,
          "std": 0.07034203003197645
        },
        "spread_std": {
          "mean": 0.0199916193766209,
          "std": 0.02074680601663185
        }
      },
      "cmp": {
        "basic_gen": {
          "depth_mean": {
            "mean": 110137.92635091145,
            "std": 116802.12986393065
          },
          "imb_mean": {
            "mean": 0.06228546922405561,
            "std": 0.05087179755935901
          },
          "imb_std": {
            "mean": 0.11578871278713147,
            "std": 0.029030843337315218
          },
          "spread_mean": {
            "mean": 0.06283239523569743,
            "std": 0.04771566533786083
          },
          "spread_std": {
            "mean": 0.021191804407862946,
            "std": 0.01867052859468154
          }
        },
        "basic_true": {
          "depth_mean": {
            "mean": 138612.64161173502,
            "std": 148318.43541847734
          },
          "imb_mean": {
            "mean": 0.02967020500606547,
            "std": 0.17427951313694295
          },
          "imb_std": {
            "mean": 0.11398454895243049,
            "std": 0.056507245937748765
          },
          "spread_mean": {
            "mean": 0.07806722323099773,
            "std": 0.07034203003197645
          },
          "spread_std": {
            "mean": 0.0199916193766209,
            "std": 0.02074680601663185
          }
        },
        "dist": {
          "depth": {
            "ks": {
              "mean": 0.6966145833333334,
              "std": 0.23480501639621415
            },
            "w1": {
              "mean": 28489.42556833476,
              "std": 36533.72253887002
            }
          },
          "imb": {
            "ks": {
              "mean": 0.4947916666666667,
              "std": 0.22182853582340473
            },
            "w1": {
              "mean": 0.14221542170202017,
              "std": 0.10916654453041316
            }
          },
          "ret": {
            "ks": {
              "mean": 0.4036458333333333,
              "std": 0.2379786614719316
            },
            "w1": {
              "mean": 0.0013464521616697311,
              "std": 0.00105188561813963
            }
          },
          "spread": {
            "ks": {
              "mean": 0.5950520833333334,
              "std": 0.2513762843822511
            },
            "w1": {
              "mean": 0.023255958532293636,
              "std": 0.032616820998950684
            }
          }
        },
        "error": {
          "imbalance_mae": {
            "mean": 1.8163211193643118,
            "std": 0.8399249263063061
          },
          "spread_mae": {
            "mean": 438.41632689918947,
            "std": 769.0207023450647
          }
        },
        "microstructure": {
          "impact_response_curve_gen": {
            "1": {
              "mean": -3.32404861326229e-05,
              "std": 0.00010937952260613432
            },
            "10": {
              "mean": -1.1269400741614846e-06,
              "std": 0.0007581322228146445
            },
            "20": {
              "mean": 8.887120560304427e-05,
              "std": 0.0015869129728828758
            },
            "5": {
              "mean": 1.2468594399054092e-06,
              "std": 0.0004066643641016087
            }
          },
          "impact_response_curve_true": {
            "1": {
              "mean": -9.022793972661327e-06,
              "std": 0.0002798241077444863
            },
            "10": {
              "mean": 0.0007390309897548344,
              "std": 0.003092702383112271
            },
            "20": {
              "mean": 0.0012952132664875654,
              "std": 0.00597434672413142
            },
            "5": {
              "mean": 0.0002660398870020231,
              "std": 0.0009784616641974207
            }
          },
          "impact_response_l1": {
            "mean": 2.633059635454378,
            "std": 3.7808956013158874
          }
        },
        "params_fit": {
          "delta_mid_rmse": {
            "mean": 0.004944319904704268,
            "std": 0.005003900168345829
          },
          "log_spread_rmse": {
            "mean": 0.41931229767700035,
            "std": 0.194108374967483
          },
          "params_mae": {
            "mean": 0.5348253399133682,
            "std": 0.21976004218636377
          },
          "params_rmse": {
            "mean": 0.7705067830781142,
            "std": 0.2374426987275477
          }
        },
        "score_main": {
          "mean": 0.3601145864940338,
          "std": 0.0
        },
        "structure": {
          "vol_corr_mae": {
            "mean": 0.3625368796448727,
            "std": 0.03793285121729559
          },
          "vol_corr_rmse": {
            "mean": 0.4470069692293977,
            "std": 0.03987918847723417
          }
        },
        "temporal": {
          "depth": {
            "acf_l1": {
              "mean": 0.3212347330129013,
              "std": 0.10910080168856949
            },
            "acf_l2": {
              "mean": 0.3898997739623891,
              "std": 0.12386872892009232
            }
          },
          "imb": {
            "acf_l1": {
              "mean": 0.40758935424933324,
              "std": 0.09707819046851249
            },
            "acf_l2": {
              "mean": 0.48600227800090784,
              "std": 0.10562237446557451
            }
          },
          "ret": {
            "acf_l1": {
              "mean": 0.24631736158101702,
              "std": 0.07675976896504422
            },
            "acf_l2": {
              "mean": 0.30716060747672197,
              "std": 0.0857176794844748
            }
          },
          "spread": {
            "acf_l1": {
              "mean": 0.32518734938691635,
              "std": 0.1255331151614158
            },
            "acf_l2": {
              "mean": 0.3814476551879767,
              "std": 0.13444196326721403
            }
          },
          "volatility": {
            "acf_l1": {
              "mean": 0.26917152971010394,
              "std": 0.11714738665220034
            },
            "acf_l2": {
              "mean": 0.32101658405882283,
              "std": 0.1270559698001872
            }
          }
        },
        "validity": {
          "ask_monotonic_violation_rate": {
            "mean": 0.0,
            "std": 0.0
          },
          "bid_monotonic_violation_rate": {
            "mean": 0.0,
            "std": 0.0
          },
          "crossed_rate": {
            "mean": 0.0,
            "std": 0.0
          },
          "nonpositive_volume_rate": {
            "mean": 0.0,
            "std": 0.0
          },
          "valid_rate": {
            "mean": 1.0,
            "std": 0.0
          }
        },
        "main": {
          "tstr_macro_f1": {
            "mean": 0.39101145012358557,
            "std": 0.0
          },
          "disc_auc": {
            "mean": 0.8302465602893707,
            "std": 0.0
          },
          "disc_auc_gap": {
            "mean": 0.3302465602893707,
            "std": 0.0
          },
          "unconditional_w1": {
            "mean": 0.2272910103068649,
            "std": 0.0
          },
          "conditional_w1": {
            "mean": 0.3450267831634632,
            "std": 0.0
          },
          "label_horizon": 3,
          "n_examples_real": 696,
          "n_examples_gen": 696,
          "threshold_abs_move": {
            "mean": 0.0010070799617096782,
            "std": 0.0
          },
          "unconditional_w1_by_stat": {
            "spread": {
              "mean": 0.21444354909873628,
              "std": 0.0
            },
            "depth": {
              "mean": 0.190882701634096,
              "std": 0.0
            },
            "imb": {
              "mean": 0.3207165889468653,
              "std": 0.0
            },
            "ret": {
              "mean": 0.18312120154776204,
              "std": 0.0
            }
          },
          "conditional_w1_by_stat": {
            "spread": {
              "mean": 0.30593992351082505,
              "std": 0.0
            },
            "depth": {
              "mean": 0.19112840046243376,
              "std": 0.0
            },
            "imb": {
              "mean": 0.6590879099545124,
              "std": 0.0
            },
            "ret": {
              "mean": 0.2239508987260816,
              "std": 0.0
            }
          },
          "stat_scales": {
            "spread": {
              "mean": 0.07601478834608773,
              "std": 0.0
            },
            "depth": {
              "mean": 149059.0906396161,
              "std": 0.0
            },
            "imb": {
              "mean": 0.2157761044529482,
              "std": 0.0
            },
            "ret": {
              "mean": 0.006012265051530788,
              "std": 0.0
            }
          }
        },
        "extra": {
          "u_l1": {
            "mean": 0.5345052083333333,
            "std": 0.0
          },
          "c_l1": {
            "mean": 111.07818336949666,
            "std": 0.0
          },
          "spread_specific_error": {
            "mean": 438.41632689918947,
            "std": 769.0207023450647
          },
          "imbalance_specific_error": {
            "mean": 1.8163211193643118,
            "std": 0.8399249263063061
          },
          "ret_vol_acf_error": {
            "mean": 0.2577444456455605,
            "std": 0.0
          },
          "impact_response_error": {
            "mean": 2.633059635454378,
            "std": 3.7808956013158874
          },
          "efficiency_ms_per_sample": {
            "mean": 334.96343856677413,
            "std": 1.0082835517099786
          }
        },
        "legacy_score_main": {
          "mean": 1.1836419770551148,
          "std": 0.2880273621626561
        }
      },
      "horizon": {
        "32": {
          "delta_mid_rmse": {
            "mean": 0.004944319904704268,
            "std": 0.005003900168345829
          },
          "log_spread_rmse": {
            "mean": 0.41931229767700035,
            "std": 0.194108374967483
          },
          "params_mae": {
            "mean": 0.5348253399133682,
            "std": 0.21976004218636377
          },
          "params_rmse": {
            "mean": 0.7705067830781142,
            "std": 0.2374426987275477
          }
        }
      },
      "timing": {
        "horizon": {
          "mean": 32.0,
          "std": 0.0
        },
        "latency_ms_per_sample": {
          "mean": 334.96343856677413,
          "std": 1.0082835517099786
        },
        "latency_ms_per_step": {
          "mean": 10.467607455211692,
          "std": 0.03150886099093683
        },
        "latency_s_total": {
          "mean": 0.33496343856677413,
          "std": 0.0010082835517099785
        },
        "nfe": {
          "mean": 2.0,
          "std": 0.0
        },
        "throughput_steps_per_s": {
          "mean": 95.53367294007403,
          "std": 0.28522704023878687
        }
      },
      "meta": {
        "n_windows": 24,
        "nfe": 2,
        "horizon": 32
      }
    },
    "128": {
      "gen": {
        "depth_mean": {
          "mean": 105700.825978597,
          "std": 111591.41180547967
        },
        "imb_mean": {
          "mean": 0.06108592693150664,
          "std": 0.04245007905174669
        },
        "imb_std": {
          "mean": 0.11647664072612922,
          "std": 0.024500885575809574
        },
        "spread_mean": {
          "mean": 0.05698279539744059,
          "std": 0.04195930649004128
        },
        "spread_std": {
          "mean": 0.018762386855087243,
          "std": 0.016109205921773045
        }
      },
      "true": {
        "depth_mean": {
          "mean": 138779.01570638022,
          "std": 148271.65267307323
        },
        "imb_mean": {
          "mean": 0.04585559124825522,
          "std": 0.14227278332378346
        },
        "imb_std": {
          "mean": 0.18147085110346475,
          "std": 0.07127182018423837
        },
        "spread_mean": {
          "mean": 0.08076916138331096,
          "std": 0.06676863064642506
        },
        "spread_std": {
          "mean": 0.03186188010537686,
          "std": 0.028828642191336476
        }
      },
      "cmp": {
        "basic_gen": {
          "depth_mean": {
            "mean": 105700.825978597,
            "std": 111591.41180547967
          },
          "imb_mean": {
            "mean": 0.06108592693150664,
            "std": 0.04245007905174669
          },
          "imb_std": {
            "mean": 0.11647664072612922,
            "std": 0.024500885575809574
          },
          "spread_mean": {
            "mean": 0.05698279539744059,
            "std": 0.04195930649004128
          },
          "spread_std": {
            "mean": 0.018762386855087243,
            "std": 0.016109205921773045
          }
        },
        "basic_true": {
          "depth_mean": {
            "mean": 138779.01570638022,
            "std": 148271.65267307323
          },
          "imb_mean": {
            "mean": 0.04585559124825522,
            "std": 0.14227278332378346
          },
          "imb_std": {
            "mean": 0.18147085110346475,
            "std": 0.07127182018423837
          },
          "spread_mean": {
            "mean": 0.08076916138331096,
            "std": 0.06676863064642506
          },
          "spread_std": {
            "mean": 0.03186188010537686,
            "std": 0.028828642191336476
          }
        },
        "dist": {
          "depth": {
            "ks": {
              "mean": 0.5315755208333334,
              "std": 0.25704667632226347
            },
            "w1": {
              "mean": 33143.5078270575,
              "std": 39833.30344357171
            }
          },
          "imb": {
            "ks": {
              "mean": 0.427734375,
              "std": 0.1119545606444353
            },
            "w1": {
              "mean": 0.13634276800618175,
              "std": 0.0580441412632809
            }
          },
          "ret": {
            "ks": {
              "mean": 0.3082682291666667,
              "std": 0.16766535048224154
            },
            "w1": {
              "mean": 0.0011160992629205186,
              "std": 0.0007425839930508964
            }
          },
          "spread": {
            "ks": {
              "mean": 0.5732421875,
              "std": 0.22264268621880498
            },
            "w1": {
              "mean": 0.0251105793674166,
              "std": 0.027953996221925796
            }
          }
        },
        "error": {
          "imbalance_mae": {
            "mean": 1.2083477283286383,
            "std": 0.24617327077852946
          },
          "spread_mae": {
            "mean": 308.2685989131457,
            "std": 688.1754401483483
          }
        },
        "microstructure": {
          "impact_response_curve_gen": {
            "1": {
              "mean": -1.7036195176105083e-05,
              "std": 3.501392210030165e-05
            },
            "10": {
              "mean": -7.871680411199206e-05,
              "std": 0.0003969703864225756
            },
            "20": {
              "mean": -0.00010232022951097363,
              "std": 0.0007667715415964404
            },
            "5": {
              "mean": -4.869674671539525e-05,
              "std": 0.00017357671918648008
            }
          },
          "impact_response_curve_true": {
            "1": {
              "mean": -1.8317025019960927e-05,
              "std": 0.0002207111164251926
            },
            "10": {
              "mean": 0.0002857665637868721,
              "std": 0.0019883584925110167
            },
            "20": {
              "mean": 0.0010366341691778703,
              "std": 0.003770250563587872
            },
            "5": {
              "mean": 2.2485294614987936e-05,
              "std": 0.0011045376964744552
            }
          },
          "impact_response_l1": {
            "mean": 1.7058509861568174,
            "std": 1.5951070241865128
          }
        },
        "params_fit": {
          "delta_mid_rmse": {
            "mean": 0.004903462703320353,
            "std": 0.004224854751882761
          },
          "log_spread_rmse": {
            "mean": 0.48883836281796295,
            "std": 0.2155736012385736
          },
          "params_mae": {
            "mean": 0.5545444153249264,
            "std": 0.23257221590888238
          },
          "params_rmse": {
            "mean": 0.8064683564007282,
            "std": 0.25689779363501436
          }
        },
        "score_main": {
          "mean": 0.39453774817570425,
          "std": 0.0
        },
        "structure": {
          "vol_corr_mae": {
            "mean": 0.2668964539333269,
            "std": 0.021996908601435584
          },
          "vol_corr_rmse": {
            "mean": 0.3306400723024024,
            "std": 0.024446132710580337
          }
        },
        "temporal": {
          "depth": {
            "acf_l1": {
              "mean": 0.31765297916509133,
              "std": 0.16618520947218907
            },
            "acf_l2": {
              "mean": 0.35409598475077075,
              "std": 0.16788089635141362
            }
          },
          "imb": {
            "acf_l1": {
              "mean": 0.4985508394401917,
              "std": 0.15771301178078906
            },
            "acf_l2": {
              "mean": 0.550572510508595,
              "std": 0.13176680938152627
            }
          },
          "ret": {
            "acf_l1": {
              "mean": 0.2751864435556241,
              "std": 0.23556986988966147
            },
            "acf_l2": {
              "mean": 0.3080436198384646,
              "std": 0.23745511187849497
            }
          },
          "spread": {
            "acf_l1": {
              "mean": 0.3277063050830185,
              "std": 0.1702760475701136
            },
            "acf_l2": {
              "mean": 0.3859221496502032,
              "std": 0.17781536917743268
            }
          },
          "volatility": {
            "acf_l1": {
              "mean": 0.15850781351097618,
              "std": 0.07509293586846405
            },
            "acf_l2": {
              "mean": 0.19065421535974467,
              "std": 0.0812889002954941
            }
          }
        },
        "validity": {
          "ask_monotonic_violation_rate": {
            "mean": 0.0,
            "std": 0.0
          },
          "bid_monotonic_violation_rate": {
            "mean": 0.0,
            "std": 0.0
          },
          "crossed_rate": {
            "mean": 0.0,
            "std": 0.0
          },
          "nonpositive_volume_rate": {
            "mean": 0.0,
            "std": 0.0
          },
          "valid_rate": {
            "mean": 1.0,
            "std": 0.0
          }
        },
        "main": {
          "tstr_macro_f1": {
            "mean": 0.3987993740677569,
            "std": 0.0
          },
          "disc_auc": {
            "mean": 0.9504276816608996,
            "std": 0.0
          },
          "disc_auc_gap": {
            "mean": 0.45042768166089964,
            "std": 0.0
          },
          "unconditional_w1": {
            "mean": 0.2802187749852096,
            "std": 0.0
          },
          "conditional_w1": {
            "mean": 0.32245744141206834,
            "std": 0.0
          },
          "label_horizon": 10,
          "n_examples_real": 2832,
          "n_examples_gen": 2832,
          "threshold_abs_move": {
            "mean": 0.003021240234375,
            "std": 0.0
          },
          "unconditional_w1_by_stat": {
            "spread": {
              "mean": 0.31113034018095775,
              "std": 0.0
            },
            "depth": {
              "mean": 0.21891530414392482,
              "std": 0.0
            },
            "imb": {
              "mean": 0.40448674518912636,
              "std": 0.0
            },
            "ret": {
              "mean": 0.18634271042682943,
              "std": 0.0
            }
          },
          "conditional_w1_by_stat": {
            "spread": {
              "mean": 0.3162511667927569,
              "std": 0.0
            },
            "depth": {
              "mean": 0.21930232583381698,
              "std": 0.0
            },
            "imb": {
              "mean": 0.564900007955497,
              "std": 0.0
            },
            "ret": {
              "mean": 0.18937626506620264,
              "std": 0.0
            }
          },
          "stat_scales": {
            "spread": {
              "mean": 0.0794007485318524,
              "std": 0.0
            },
            "depth": {
              "mean": 151131.58376702765,
              "std": 0.0
            },
            "imb": {
              "mean": 0.24135734835557462,
              "std": 0.0
            },
            "ret": {
              "mean": 0.005893554097343454,
              "std": 0.0
            }
          }
        },
        "extra": {
          "u_l1": {
            "mean": 0.552734375,
            "std": 0.0
          },
          "c_l1": {
            "mean": 78.02467568449175,
            "std": 0.0
          },
          "spread_specific_error": {
            "mean": 308.2685989131457,
            "std": 688.1754401483483
          },
          "imbalance_specific_error": {
            "mean": 1.2083477283286383,
            "std": 0.24617327077852946
          },
          "ret_vol_acf_error": {
            "mean": 0.21684712853330013,
            "std": 0.0
          },
          "impact_response_error": {
            "mean": 1.7058509861568174,
            "std": 1.5951070241865128
          },
          "efficiency_ms_per_sample": {
            "mean": 1340.3352719421189,
            "std": 1.3952855905045969
          }
        },
        "legacy_score_main": {
          "mean": 1.2442242465928712,
          "std": 0.18151303278194098
        }
      },
      "horizon": {
        "128": {
          "delta_mid_rmse": {
            "mean": 0.004903462703320353,
            "std": 0.004224854751882761
          },
          "log_spread_rmse": {
            "mean": 0.48883836281796295,
            "std": 0.2155736012385736
          },
          "params_mae": {
            "mean": 0.5545444153249264,
            "std": 0.23257221590888238
          },
          "params_rmse": {
            "mean": 0.8064683564007282,
            "std": 0.25689779363501436
          }
        },
        "32": {
          "delta_mid_rmse": {
            "mean": 0.004030791900731856,
            "std": 0.0033993043877057817
          },
          "log_spread_rmse": {
            "mean": 0.4178264656414588,
            "std": 0.2102528404820152
          },
          "params_mae": {
            "mean": 0.5531399622559547,
            "std": 0.25014198251005876
          },
          "params_rmse": {
            "mean": 0.7990854009985924,
            "std": 0.2863181702782829
          }
        }
      },
      "timing": {
        "horizon": {
          "mean": 128.0,
          "std": 0.0
        },
        "latency_ms_per_sample": {
          "mean": 1340.3352719421189,
          "std": 1.3952855905045969
        },
        "latency_ms_per_step": {
          "mean": 10.471369312047804,
          "std": 0.010900668675817163
        },
        "latency_s_total": {
          "mean": 1.3403352719421189,
          "std": 0.0013952855905045968
        },
        "nfe": {
          "mean": 2.0,
          "std": 0.0
        },
        "throughput_steps_per_s": {
          "mean": 95.4985974516551,
          "std": 0.0993241344166787
        }
      },
      "meta": {
        "n_windows": 24,
        "nfe": 2,
        "horizon": 128
      }
    },
    "512": {
      "gen": {
        "depth_mean": {
          "mean": 104856.52315266927,
          "std": 110503.04782383221
        },
        "imb_mean": {
          "mean": 0.05718974307334671,
          "std": 0.036473385929649105
        },
        "imb_std": {
          "mean": 0.11885885087152322,
          "std": 0.02401193522822013
        },
        "spread_mean": {
          "mean": 0.04993740220864614,
          "std": 0.035262801963128844
        },
        "spread_std": {
          "mean": 0.01627908672768778,
          "std": 0.013428833188883943
        }
      },
      "true": {
        "depth_mean": {
          "mean": 143510.03164672852,
          "std": 144617.41991037386
        },
        "imb_mean": {
          "mean": 0.041967253938006856,
          "std": 0.0664428546064421
        },
        "imb_std": {
          "mean": 0.21701716290165982,
          "std": 0.07007523507857412
        },
        "spread_mean": {
          "mean": 0.07624854395786922,
          "std": 0.06202319802652845
        },
        "spread_std": {
          "mean": 0.0393167848160374,
          "std": 0.03656753328809206
        }
      },
      "cmp": {
        "basic_gen": {
          "depth_mean": {
            "mean": 104856.52315266927,
            "std": 110503.04782383221
          },
          "imb_mean": {
            "mean": 0.05718974307334671,
            "std": 0.036473385929649105
          },
          "imb_std": {
            "mean": 0.11885885087152322,
            "std": 0.02401193522822013
          },
          "spread_mean": {
            "mean": 0.04993740220864614,
            "std": 0.035262801963128844
          },
          "spread_std": {
            "mean": 0.01627908672768778,
            "std": 0.013428833188883943
          }
        },
        "basic_true": {
          "depth_mean": {
            "mean": 143510.03164672852,
            "std": 144617.41991037386
          },
          "imb_mean": {
            "mean": 0.041967253938006856,
            "std": 0.0664428546064421
          },
          "imb_std": {
            "mean": 0.21701716290165982,
            "std": 0.07007523507857412
          },
          "spread_mean": {
            "mean": 0.07624854395786922,
            "std": 0.06202319802652845
          },
          "spread_std": {
            "mean": 0.0393167848160374,
            "std": 0.03656753328809206
          }
        },
        "dist": {
          "depth": {
            "ks": {
              "mean": 0.500732421875,
              "std": 0.2467128897436608
            },
            "w1": {
              "mean": 38689.15956401814,
              "std": 40277.4337497214
            }
          },
          "imb": {
            "ks": {
              "mean": 0.23746744791666666,
              "std": 0.07207824424463469
            },
            "w1": {
              "mean": 0.097258001970571,
              "std": 0.04365338701397207
            }
          },
          "ret": {
            "ks": {
              "mean": 0.2696126302083333,
              "std": 0.12234666526658906
            },
            "w1": {
              "mean": 0.001021650583425071,
              "std": 0.0006534512090505771
            }
          },
          "spread": {
            "ks": {
              "mean": 0.5584309895833334,
              "std": 0.15242814989250586
            },
            "w1": {
              "mean": 0.029103184390502673,
              "std": 0.02874648617568834
            }
          }
        },
        "error": {
          "imbalance_mae": {
            "mean": 0.9557616193258417,
            "std": 0.06397709392876644
          },
          "spread_mae": {
            "mean": 1.1015698306802584,
            "std": 0.6638639910984239
          }
        },
        "microstructure": {
          "impact_response_curve_gen": {
            "1": {
              "mean": -2.0203886660865002e-05,
              "std": 2.3758098146772812e-05
            },
            "10": {
              "mean": -0.00021751801321470956,
              "std": 0.00017949330312829915
            },
            "20": {
              "mean": -0.00043888505744901605,
              "std": 0.0003639559992818809
            },
            "5": {
              "mean": -0.00010877663065281407,
              "std": 9.143392196374152e-05
            }
          },
          "impact_response_curve_true": {
            "1": {
              "mean": 2.0773297060399976e-05,
              "std": 7.898649321006008e-05
            },
            "10": {
              "mean": 0.0002103022507125188,
              "std": 0.0007790770822816255
            },
            "20": {
              "mean": 0.0003014869474753067,
              "std": 0.0013073509996374343
            },
            "5": {
              "mean": 0.00010750937874015822,
              "std": 0.00041430504134736836
            }
          },
          "impact_response_l1": {
            "mean": 3.1031435389664246,
            "std": 7.21840222775002
          }
        },
        "params_fit": {
          "delta_mid_rmse": {
            "mean": 0.004599344948170862,
            "std": 0.0036631313718637547
          },
          "log_spread_rmse": {
            "mean": 0.5503468892226616,
            "std": 0.2720958022552299
          },
          "params_mae": {
            "mean": 0.5871995066603025,
            "std": 0.307860192136747
          },
          "params_rmse": {
            "mean": 0.8622957207262516,
            "std": 0.4013399835695468
          }
        },
        "score_main": {
          "mean": 0.4050362363013047,
          "std": 0.0
        },
        "structure": {
          "vol_corr_mae": {
            "mean": 0.18728068064480044,
            "std": 0.0926811264174315
          },
          "vol_corr_rmse": {
            "mean": 0.23057887532448262,
            "std": 0.09155908676838982
          }
        },
        "temporal": {
          "depth": {
            "acf_l1": {
              "mean": 0.4567941316398838,
              "std": 0.15336825958468014
            },
            "acf_l2": {
              "mean": 0.47433390398458625,
              "std": 0.1470022404681574
            }
          },
          "imb": {
            "acf_l1": {
              "mean": 0.6439653459210173,
              "std": 0.10973998875539401
            },
            "acf_l2": {
              "mean": 0.668812061013798,
              "std": 0.0875541438618592
            }
          },
          "ret": {
            "acf_l1": {
              "mean": 0.33712779834764434,
              "std": 0.30995347219211694
            },
            "acf_l2": {
              "mean": 0.351691857418105,
              "std": 0.3095309256437885
            }
          },
          "spread": {
            "acf_l1": {
              "mean": 0.4594286540367687,
              "std": 0.18969167927307018
            },
            "acf_l2": {
              "mean": 0.490703821704699,
              "std": 0.17921694979583935
            }
          },
          "volatility": {
            "acf_l1": {
              "mean": 0.12131338350313758,
              "std": 0.05461190120059964
            },
            "acf_l2": {
              "mean": 0.13850694804989525,
              "std": 0.058671940952690634
            }
          }
        },
        "validity": {
          "ask_monotonic_violation_rate": {
            "mean": 0.0,
            "std": 0.0
          },
          "bid_monotonic_violation_rate": {
            "mean": 0.0,
            "std": 0.0
          },
          "crossed_rate": {
            "mean": 0.0,
            "std": 0.0
          },
          "nonpositive_volume_rate": {
            "mean": 0.0,
            "std": 0.0
          },
          "valid_rate": {
            "mean": 1.0,
            "std": 0.0
          }
        },
        "main": {
          "tstr_macro_f1": {
            "mean": 0.3907061367126688,
            "std": 0.0
          },
          "disc_auc": {
            "mean": 0.9923351940388007,
            "std": 0.0
          },
          "disc_auc_gap": {
            "mean": 0.49233519403880066,
            "std": 0.0
          },
          "unconditional_w1": {
            "mean": 0.2876714870094146,
            "std": 0.0
          },
          "conditional_w1": {
            "mean": 0.30431806599096106,
            "std": 0.0
          },
          "label_horizon": 10,
          "n_examples_real": 12048,
          "n_examples_gen": 12048,
          "threshold_abs_move": {
            "mean": 0.00311279296875,
            "std": 0.0
          },
          "unconditional_w1_by_stat": {
            "spread": {
              "mean": 0.3418591416460074,
              "std": 0.0
            },
            "depth": {
              "mean": 0.25784940990088645,
              "std": 0.0
            },
            "imb": {
              "mean": 0.3637311465452092,
              "std": 0.0
            },
            "ret": {
              "mean": 0.18724624994555517,
              "std": 0.0
            }
          },
          "conditional_w1_by_stat": {
            "spread": {
              "mean": 0.35475771104890635,
              "std": 0.0
            },
            "depth": {
              "mean": 0.2577750652255906,
              "std": 0.0
            },
            "imb": {
              "mean": 0.4094498007825765,
              "std": 0.0
            },
            "ret": {
              "mean": 0.19528968690677084,
              "std": 0.0
            }
          },
          "stat_scales": {
            "spread": {
              "mean": 0.08203679154556996,
              "std": 0.0
            },
            "depth": {
              "mean": 150088.8362889541,
              "std": 0.0
            },
            "imb": {
              "mean": 0.23753339673064425,
              "std": 0.0
            },
            "ret": {
              "mean": 0.005231462037792072,
              "std": 0.0
            }
          }
        },
        "extra": {
          "u_l1": {
            "mean": 0.5319417317708334,
            "std": 0.0
          },
          "c_l1": {
            "mean": 1.0543024029759858,
            "std": 0.0
          },
          "spread_specific_error": {
            "mean": 1.1015698306802584,
            "std": 0.6638639910984239
          },
          "imbalance_specific_error": {
            "mean": 0.9557616193258417,
            "std": 0.06397709392876644
          },
          "ret_vol_acf_error": {
            "mean": 0.22922059092539096,
            "std": 0.0
          },
          "impact_response_error": {
            "mean": 3.1031435389664246,
            "std": 7.21840222775002
          },
          "efficiency_ms_per_sample": {
            "mean": 5365.818409404407,
            "std": 6.328963139582104
          }
        },
        "legacy_score_main": {
          "mean": 1.3268063560183947,
          "std": 0.25914918110928864
        }
      },
      "horizon": {
        "128": {
          "delta_mid_rmse": {
            "mean": 0.005090343804719548,
            "std": 0.004332344928213485
          },
          "log_spread_rmse": {
            "mean": 0.4676610653599103,
            "std": 0.25691932007893425
          },
          "params_mae": {
            "mean": 0.5614397761722406,
            "std": 0.2452618061165451
          },
          "params_rmse": {
            "mean": 0.8171346945067247,
            "std": 0.2855029087810496
          }
        },
        "32": {
          "delta_mid_rmse": {
            "mean": 0.0038732862473504306,
            "std": 0.0032077431809486236
          },
          "log_spread_rmse": {
            "mean": 0.44345427801211673,
            "std": 0.23692934260226142
          },
          "params_mae": {
            "mean": 0.5641428455710411,
            "std": 0.2473564978766371
          },
          "params_rmse": {
            "mean": 0.8198912193377813,
            "std": 0.29111628989405997
          }
        },
        "512": {
          "delta_mid_rmse": {
            "mean": 0.004599344948170862,
            "std": 0.0036631313718637547
          },
          "log_spread_rmse": {
            "mean": 0.5503468892226616,
            "std": 0.2720958022552299
          },
          "params_mae": {
            "mean": 0.5871995066603025,
            "std": 0.307860192136747
          },
          "params_rmse": {
            "mean": 0.8622957207262516,
            "std": 0.4013399835695468
          }
        }
      },
      "timing": {
        "horizon": {
          "mean": 512.0,
          "std": 0.0
        },
        "latency_ms_per_sample": {
          "mean": 5365.818409404407,
          "std": 6.328963139582104
        },
        "latency_ms_per_step": {
          "mean": 10.480114080867983,
          "std": 0.012361256131996297
        },
        "latency_s_total": {
          "mean": 5.365818409404407,
          "std": 0.006328963139582104
        },
        "nfe": {
          "mean": 2.0,
          "std": 0.0
        },
        "throughput_steps_per_s": {
          "mean": 95.41894125615238,
          "std": 0.11243525091446555
        }
      },
      "meta": {
        "n_windows": 24,
        "nfe": 2,
        "horizon": 512
      }
    }
  }
}
