{
  "rows": [
    {
      "variant": "baseline_fm",
      "checkpoint": 1000,
      "n": 3,
      "score_main": {
        "mean": 2.692425717046216,
        "std": 0.2899493572599455,
        "n": 3
      },
      "tstr_macro_f1": {
        "mean": 0.17729827357368508,
        "std": 0.01712127834485056,
        "n": 3
      },
      "disc_auc_gap": {
        "mean": 0.5,
        "std": 0.0,
        "n": 3
      },
      "unconditional_w1": {
        "mean": 277.6807313522331,
        "std": 171.70876578378818,
        "n": 3
      },
      "conditional_w1": {
        "mean": 264.7951058990039,
        "std": 162.0240179375142,
        "n": 3
      }
    },
    {
      "variant": "baseline_fm",
      "checkpoint": 2000,
      "n": 3,
      "score_main": {
        "mean": 1.9909494588002454,
        "std": 0.1605353138536411,
        "n": 3
      },
      "tstr_macro_f1": {
        "mean": 0.21478364509823655,
        "std": 0.038075676699686964,
        "n": 3
      },
      "disc_auc_gap": {
        "mean": 0.4999957850859529,
        "std": 5.866659036202298e-06,
        "n": 3
      },
      "unconditional_w1": {
        "mean": 84.97680181202657,
        "std": 50.546883436439,
        "n": 3
      },
      "conditional_w1": {
        "mean": 80.14937235936303,
        "std": 47.14630829561024,
        "n": 3
      }
    },
    {
      "variant": "baseline_fm",
      "checkpoint": 4000,
      "n": 3,
      "score_main": {
        "mean": 1.9880827023287635,
        "std": 0.3906269017440899,
        "n": 3
      },
      "tstr_macro_f1": {
        "mean": 0.2048709333513058,
        "std": 0.007383715840661358,
        "n": 3
      },
      "disc_auc_gap": {
        "mean": 0.49901056885559303,
        "std": 0.0002397919751765722,
        "n": 3
      },
      "unconditional_w1": {
        "mean": 54.18846453774359,
        "std": 55.067093485643,
        "n": 3
      },
      "conditional_w1": {
        "mean": 53.45268818425833,
        "std": 54.310026942382024,
        "n": 3
      }
    },
    {
      "variant": "baseline_fm",
      "checkpoint": 8000,
      "n": 3,
      "score_main": {
        "mean": 1.9945057473672012,
        "std": 0.3041962998871939,
        "n": 3
      },
      "tstr_macro_f1": {
        "mean": 0.21060494416341435,
        "std": 0.012844747894339446,
        "n": 3
      },
      "disc_auc_gap": {
        "mean": 0.4988415181335568,
        "std": 0.0010749738761905293,
        "n": 3
      },
      "unconditional_w1": {
        "mean": 60.258390670862234,
        "std": 34.37310162337386,
        "n": 3
      },
      "conditional_w1": {
        "mean": 59.19918431606421,
        "std": 33.73529495378729,
        "n": 3
      }
    },
    {
      "variant": "baseline_fm",
      "checkpoint": 12000,
      "n": 3,
      "score_main": {
        "mean": 1.6945017542851668,
        "std": 0.4786890269810071,
        "n": 3
      },
      "tstr_macro_f1": {
        "mean": 0.22062484243526603,
        "std": 0.014312875553352443,
        "n": 3
      },
      "disc_auc_gap": {
        "mean": 0.4975420041491143,
        "std": 0.00177843380923303,
        "n": 3
      },
      "unconditional_w1": {
        "mean": 53.54070044932945,
        "std": 65.85497046244983,
        "n": 3
      },
      "conditional_w1": {
        "mean": 53.16366349009136,
        "std": 65.314632171662,
        "n": 3
      }
    },
    {
      "variant": "baseline_fm",
      "checkpoint": 16000,
      "n": 3,
      "score_main": {
        "mean": 1.8726731617249763,
        "std": 0.21003115676946588,
        "n": 3
      },
      "tstr_macro_f1": {
        "mean": 0.21177823088198897,
        "std": 0.014588717678424776,
        "n": 3
      },
      "disc_auc_gap": {
        "mean": 0.4993873363228316,
        "std": 0.00047636853315730413,
        "n": 3
      },
      "unconditional_w1": {
        "mean": 56.20130272399118,
        "std": 31.65635739573501,
        "n": 3
      },
      "conditional_w1": {
        "mean": 55.7252353315018,
        "std": 31.406974993205157,
        "n": 3
      }
    },
    {
      "variant": "baseline_fm",
      "checkpoint": 20000,
      "n": 3,
      "score_main": {
        "mean": 1.9635025691555252,
        "std": 0.36980101130498066,
        "n": 3
      },
      "tstr_macro_f1": {
        "mean": 0.19262078264473423,
        "std": 0.0133635541185738,
        "n": 3
      },
      "disc_auc_gap": {
        "mean": 0.4996906242018589,
        "std": 0.00020057680531614528,
        "n": 3
      },
      "unconditional_w1": {
        "mean": 94.49968029459512,
        "std": 75.27854306189501,
        "n": 3
      },
      "conditional_w1": {
        "mean": 93.28486737946258,
        "std": 74.90308856942842,
        "n": 3
      }
    },
    {
      "variant": "conditional_current_matching",
      "checkpoint": 1000,
      "n": 3,
      "score_main": {
        "mean": 2.6098429575382625,
        "std": 0.3204700341410126,
        "n": 3
      },
      "tstr_macro_f1": {
        "mean": 0.17559525304234916,
        "std": 0.0030566386021611542,
        "n": 3
      },
      "disc_auc_gap": {
        "mean": 0.5,
        "std": 0.0,
        "n": 3
      },
      "unconditional_w1": {
        "mean": 237.031672244298,
        "std": 151.6724695923189,
        "n": 3
      },
      "conditional_w1": {
        "mean": 228.26471547354626,
        "std": 144.84039249876764,
        "n": 3
      }
    },
    {
      "variant": "conditional_current_matching",
      "checkpoint": 2000,
      "n": 3,
      "score_main": {
        "mean": 1.8129805293786199,
        "std": 0.12439417530142889,
        "n": 3
      },
      "tstr_macro_f1": {
        "mean": 0.1750882476600133,
        "std": 0.013062979166106907,
        "n": 3
      },
      "disc_auc_gap": {
        "mean": 0.49999992660119497,
        "std": 1.038015855670531e-07,
        "n": 3
      },
      "unconditional_w1": {
        "mean": 52.48778313045569,
        "std": 34.684108045367225,
        "n": 3
      },
      "conditional_w1": {
        "mean": 51.19430195001815,
        "std": 33.69158789394258,
        "n": 3
      }
    },
    {
      "variant": "conditional_current_matching",
      "checkpoint": 4000,
      "n": 3,
      "score_main": {
        "mean": 1.8073835051964782,
        "std": 0.6313513136064951,
        "n": 3
      },
      "tstr_macro_f1": {
        "mean": 0.2031937051850948,
        "std": 0.00748605740391541,
        "n": 3
      },
      "disc_auc_gap": {
        "mean": 0.5,
        "std": 0.0,
        "n": 3
      },
      "unconditional_w1": {
        "mean": 73.64612351266878,
        "std": 94.10471406887348,
        "n": 3
      },
      "conditional_w1": {
        "mean": 73.33155132186621,
        "std": 93.7049107086952,
        "n": 3
      }
    },
    {
      "variant": "conditional_current_matching",
      "checkpoint": 8000,
      "n": 3,
      "score_main": {
        "mean": 1.8689519511954835,
        "std": 0.12689080534955632,
        "n": 3
      },
      "tstr_macro_f1": {
        "mean": 0.22961684896067663,
        "std": 0.005859035048415034,
        "n": 2
      },
      "disc_auc_gap": {
        "mean": 0.4999987764981663,
        "std": 1.730292886805288e-06,
        "n": 3
      },
      "unconditional_w1": {
        "mean": 35.36726681877443,
        "std": 16.830638441932074,
        "n": 3
      },
      "conditional_w1": {
        "mean": 34.95302457118169,
        "std": 16.5292370059579,
        "n": 3
      }
    },
    {
      "variant": "conditional_current_matching",
      "checkpoint": 12000,
      "n": 3,
      "score_main": {
        "mean": 1.63553607970627,
        "std": 0.7423051848680027,
        "n": 3
      },
      "tstr_macro_f1": {
        "mean": 0.19649808205540545,
        "std": 0.03564422185685576,
        "n": 3
      },
      "disc_auc_gap": {
        "mean": 0.4999940227649271,
        "std": 7.310827578934203e-06,
        "n": 3
      },
      "unconditional_w1": {
        "mean": 47.500452823959954,
        "std": 61.57998885607511,
        "n": 3
      },
      "conditional_w1": {
        "mean": 47.47253712499249,
        "std": 61.57514873707911,
        "n": 3
      }
    },
    {
      "variant": "conditional_current_matching",
      "checkpoint": 16000,
      "n": 3,
      "score_main": {
        "mean": 1.6253812804111494,
        "std": 0.0920391263683343,
        "n": 3
      },
      "tstr_macro_f1": {
        "mean": 0.19065936152823468,
        "std": 0.021273764065247905,
        "n": 3
      },
      "disc_auc_gap": {
        "mean": 0.49998344765672126,
        "std": 2.34085483539041e-05,
        "n": 3
      },
      "unconditional_w1": {
        "mean": 32.355956084606326,
        "std": 19.475242429750196,
        "n": 3
      },
      "conditional_w1": {
        "mean": 32.12568997191116,
        "std": 19.250156290942794,
        "n": 3
      }
    },
    {
      "variant": "conditional_current_matching",
      "checkpoint": 20000,
      "n": 3,
      "score_main": {
        "mean": 1.6499228881683095,
        "std": 0.36407763586081693,
        "n": 3
      },
      "tstr_macro_f1": {
        "mean": 0.18558066062152848,
        "std": 0.03060553777277201,
        "n": 3
      },
      "disc_auc_gap": {
        "mean": 0.5,
        "std": 0.0,
        "n": 3
      },
      "unconditional_w1": {
        "mean": 54.087097978571,
        "std": 42.29633765899575,
        "n": 3
      },
      "conditional_w1": {
        "mean": 53.82585265321635,
        "std": 42.27820648275689,
        "n": 3
      }
    },
    {
      "variant": "local_causal_ot",
      "checkpoint": 1000,
      "n": 3,
      "score_main": {
        "mean": 2.6503954991717134,
        "std": 0.30939658739669934,
        "n": 3
      },
      "tstr_macro_f1": {
        "mean": 0.1979362147287992,
        "std": 0.004741333733871379,
        "n": 3
      },
      "disc_auc_gap": {
        "mean": 0.5,
        "std": 0.0,
        "n": 3
      },
      "unconditional_w1": {
        "mean": 284.42989119413863,
        "std": 180.9080979346131,
        "n": 3
      },
      "conditional_w1": {
        "mean": 271.6631212555786,
        "std": 171.17600364732368,
        "n": 3
      }
    },
    {
      "variant": "local_causal_ot",
      "checkpoint": 2000,
      "n": 3,
      "score_main": {
        "mean": 1.7640159182152149,
        "std": 0.19210554692288564,
        "n": 3
      },
      "tstr_macro_f1": {
        "mean": 0.22605925332824228,
        "std": 0.03246831626082174,
        "n": 3
      },
      "disc_auc_gap": {
        "mean": 0.49999976811407687,
        "std": 3.279362174397895e-07,
        "n": 3
      },
      "unconditional_w1": {
        "mean": 57.35701040205916,
        "std": 40.849968546279285,
        "n": 3
      },
      "conditional_w1": {
        "mean": 55.795398162722506,
        "std": 39.48194108633887,
        "n": 3
      }
    },
    {
      "variant": "local_causal_ot",
      "checkpoint": 4000,
      "n": 3,
      "score_main": {
        "mean": 1.7797283726841886,
        "std": 0.600817965127534,
        "n": 3
      },
      "tstr_macro_f1": {
        "mean": 0.2188015055782858,
        "std": 0.044884031067882114,
        "n": 3
      },
      "disc_auc_gap": {
        "mean": 0.49999692082424857,
        "std": 4.354612108550833e-06,
        "n": 3
      },
      "unconditional_w1": {
        "mean": 60.55012635932132,
        "std": 75.43389630368486,
        "n": 3
      },
      "conditional_w1": {
        "mean": 60.15325153422844,
        "std": 74.90670765306811,
        "n": 3
      }
    },
    {
      "variant": "local_causal_ot",
      "checkpoint": 8000,
      "n": 3,
      "score_main": {
        "mean": 1.8878013894728027,
        "std": 0.4444398550460239,
        "n": 3
      },
      "tstr_macro_f1": {
        "mean": 0.2001188280824083,
        "std": 0.012978554937376055,
        "n": 3
      },
      "disc_auc_gap": {
        "mean": 0.4998771958975772,
        "std": 0.00012821813059143544,
        "n": 3
      },
      "unconditional_w1": {
        "mean": 75.77578781077372,
        "std": 61.49813947305297,
        "n": 3
      },
      "conditional_w1": {
        "mean": 75.53428254569687,
        "std": 61.379957461031985,
        "n": 3
      }
    },
    {
      "variant": "local_causal_ot",
      "checkpoint": 12000,
      "n": 3,
      "score_main": {
        "mean": 1.5269915536377772,
        "std": 0.3521800903299276,
        "n": 3
      },
      "tstr_macro_f1": {
        "mean": 0.19412537164783372,
        "std": 0.01832519188146932,
        "n": 3
      },
      "disc_auc_gap": {
        "mean": 0.49994621167466985,
        "std": 7.528961063718097e-05,
        "n": 3
      },
      "unconditional_w1": {
        "mean": 32.22726647315293,
        "std": 37.323114457846735,
        "n": 3
      },
      "conditional_w1": {
        "mean": 32.15667424823842,
        "std": 37.16794200160981,
        "n": 3
      }
    },
    {
      "variant": "local_causal_ot",
      "checkpoint": 16000,
      "n": 3,
      "score_main": {
        "mean": 1.6668857956946905,
        "std": 0.29970289990430227,
        "n": 3
      },
      "tstr_macro_f1": {
        "mean": 0.20405001450169055,
        "std": 0.030795127060479974,
        "n": 3
      },
      "disc_auc_gap": {
        "mean": 0.4997762934991299,
        "std": 0.0003029398524929352,
        "n": 3
      },
      "unconditional_w1": {
        "mean": 52.83257160271567,
        "std": 33.478202563742386,
        "n": 3
      },
      "conditional_w1": {
        "mean": 52.521249616610135,
        "std": 33.23477579815631,
        "n": 3
      }
    },
    {
      "variant": "local_causal_ot",
      "checkpoint": 20000,
      "n": 3,
      "score_main": {
        "mean": 1.680100542427932,
        "std": 0.2859064018705333,
        "n": 3
      },
      "tstr_macro_f1": {
        "mean": 0.2064821292692954,
        "std": 0.035419868136052426,
        "n": 3
      },
      "disc_auc_gap": {
        "mean": 0.4997228895484454,
        "std": 0.00034823017638555573,
        "n": 3
      },
      "unconditional_w1": {
        "mean": 52.61676136914097,
        "std": 33.30090825168512,
        "n": 3
      },
      "conditional_w1": {
        "mean": 52.1113700614776,
        "std": 32.887400165341525,
        "n": 3
      }
    }
  ]
}
